Workbook

Sheet Summary
B1: Stage 1 Discover · Output schema dashboard
B2: DDD Phase 1 · Steps 01, 03 and 04 · Talentra hackathon · Schema v1.4 · every number below is counted live from the Tree, Schema register and Allowed values sheets
B4: TOTAL PARAMETERS | D4: L1 · MACRO | E4: L2 · MICRO | F4: L3 · NANO | G4: L4 · PICO | H4: ALLOWED VALUES
B5: =COUNTIF(Tree!$E$2:$E$170,1)+COUNTIF(Tree!$E$2:$E$170,2)+COUNTIF(Tree!$E$2:$E$170,3) | D5: =COUNTIF(Tree!$E$2:$E$170,1) | E5: =COUNTIF(Tree!$E$2:$E$170,2) | F5: =COUNTIF(Tree!$E$2:$E$170,3) | G5: =COUNTIFS(Tree!$E$2:$E$170,3,Tree!$J$2:$J$170,"atomic") | H5: =COUNTA('Allowed values'!$B$2:$B$195)
B6: L1 + L2 + L3 nodes in the tree | D6: Sections | E6: Parameters | F6: Sub-parameters | G6: Atomic definitions | H6: Codes in the lists
B7: ="Total parameters "&B5&" = "&D5&" Macro (L1) + "&E5&" Micro (L2) + "&F5&" Nano (L3). Each atomic item carries its L4 Pico definition ("&G5&"); "&H5&" allowed values sit inside the lists. Without the section headings the count is "&(E5+F5)&" parameters."
B9: Parameters by step and deliverable
B10: Deliverable | C10: Grain / Section ID | D10: Name | E10: L1 Macro | F10: L2 Micro | G10: L3 Nano | H10: Total parameters | I10: Allowed values | J10: L4 atomic | K10: Share of total
B11: Step 01 | C11: one row per requirement | D11: Requirements docket | E11: =COUNTIFS(Tree!$A$2:$A$170,$B11,Tree!$E$2:$E$170,1) | F11: =COUNTIFS(Tree!$A$2:$A$170,$B11,Tree!$E$2:$E$170,2) | G11: =COUNTIFS(Tree!$A$2:$A$170,$B11,Tree!$E$2:$E$170,3) | H11: =E11+F11+G11 | I11: =SUMIF($B$18:$B$35,$B11,$I$18:$I$35) | J11: =COUNTIFS(Tree!$A$2:$A$170,$B11,Tree!$E$2:$E$170,3,Tree!$J$2:$J$170,"atomic") | K11: =H11/$H$14
B12: Step 03 | C12: one row per feature; one per feature and competitor | D12: Feature discovery | E12: =COUNTIFS(Tree!$A$2:$A$170,$B12,Tree!$E$2:$E$170,1) | F12: =COUNTIFS(Tree!$A$2:$A$170,$B12,Tree!$E$2:$E$170,2) | G12: =COUNTIFS(Tree!$A$2:$A$170,$B12,Tree!$E$2:$E$170,3) | H12: =E12+F12+G12 | I12: =SUMIF($B$18:$B$35,$B12,$I$18:$I$35) | J12: =COUNTIFS(Tree!$A$2:$A$170,$B12,Tree!$E$2:$E$170,3,Tree!$J$2:$J$170,"atomic") | K12: =H12/$H$14
B13: Step 04 | C13: one row per NFR | D13: NFR register | E13: =COUNTIFS(Tree!$A$2:$A$170,$B13,Tree!$E$2:$E$170,1) | F13: =COUNTIFS(Tree!$A$2:$A$170,$B13,Tree!$E$2:$E$170,2) | G13: =COUNTIFS(Tree!$A$2:$A$170,$B13,Tree!$E$2:$E$170,3) | H13: =E13+F13+G13 | I13: =SUMIF($B$18:$B$35,$B13,$I$18:$I$35) | J13: =COUNTIFS(Tree!$A$2:$A$170,$B13,Tree!$E$2:$E$170,3,Tree!$J$2:$J$170,"atomic") | K13: =H13/$H$14
B14: Total | D14: All deliverables | E14: =SUM(E11:E13) | F14: =SUM(F11:F13) | G14: =SUM(G11:G13) | H14: =SUM(H11:H13) | I14: =SUM(I11:I13)+I37 | J14: =SUM(J11:J13) | K14: =SUM(K11:K13)
B16: Parameters by section (L1): the tree, counted | F16: Blue = Step 03 Feature Discovery (SEC-01 to 08) Green = Step 04 NFR Discovery (SEC-09 to 13) Amber = Step 01 Requirement Analysis Docket (SEC-14 to 18)
B17: Deliverable | C17: Section ID | D17: Section (L1 Macro) | E17: L1 | F17: L2 Micro | G17: L3 Nano | H17: Total parameters | I17: Allowed values | J17: L4 atomic | K17: Share of deliverable
B18: Step 03 | C18: SEC-01 | D18: Study Frame | E18: =COUNTIFS(Tree!$B$2:$B$170,$C18,Tree!$E$2:$E$170,1) | F18: =COUNTIFS(Tree!$B$2:$B$170,$C18,Tree!$E$2:$E$170,2) | G18: =COUNTIFS(Tree!$B$2:$B$170,$C18,Tree!$E$2:$E$170,3) | H18: =E18+F18+G18 | I18: =COUNTIF('Allowed values'!$E$2:$E$195,$C18) | J18: =COUNTIFS(Tree!$B$2:$B$170,$C18,Tree!$E$2:$E$170,3,Tree!$J$2:$J$170,"atomic") | K18: =H18/SUMIF($B$18:$B$35,$B18,$H$18:$H$35)
B19: Step 03 | C19: SEC-02 | D19: Competitors Studied | E19: =COUNTIFS(Tree!$B$2:$B$170,$C19,Tree!$E$2:$E$170,1) | F19: =COUNTIFS(Tree!$B$2:$B$170,$C19,Tree!$E$2:$E$170,2) | G19: =COUNTIFS(Tree!$B$2:$B$170,$C19,Tree!$E$2:$E$170,3) | H19: =E19+F19+G19 | I19: =COUNTIF('Allowed values'!$E$2:$E$195,$C19) | J19: =COUNTIFS(Tree!$B$2:$B$170,$C19,Tree!$E$2:$E$170,3,Tree!$J$2:$J$170,"atomic") | K19: =H19/SUMIF($B$18:$B$35,$B19,$H$18:$H$35)
B20: Step 03 | C20: SEC-03 | D20: Feature Inventory | E20: =COUNTIFS(Tree!$B$2:$B$170,$C20,Tree!$E$2:$E$170,1) | F20: =COUNTIFS(Tree!$B$2:$B$170,$C20,Tree!$E$2:$E$170,2) | G20: =COUNTIFS(Tree!$B$2:$B$170,$C20,Tree!$E$2:$E$170,3) | H20: =E20+F20+G20 | I20: =COUNTIF('Allowed values'!$E$2:$E$195,$C20) | J20: =COUNTIFS(Tree!$B$2:$B$170,$C20,Tree!$E$2:$E$170,3,Tree!$J$2:$J$170,"atomic") | K20: =H20/SUMIF($B$18:$B$35,$B20,$H$18:$H$35)
B21: Step 03 | C21: SEC-04 | D21: Feature Classification | E21: =COUNTIFS(Tree!$B$2:$B$170,$C21,Tree!$E$2:$E$170,1) | F21: =COUNTIFS(Tree!$B$2:$B$170,$C21,Tree!$E$2:$E$170,2) | G21: =COUNTIFS(Tree!$B$2:$B$170,$C21,Tree!$E$2:$E$170,3) | H21: =E21+F21+G21 | I21: =COUNTIF('Allowed values'!$E$2:$E$195,$C21) | J21: =COUNTIFS(Tree!$B$2:$B$170,$C21,Tree!$E$2:$E$170,3,Tree!$J$2:$J$170,"atomic") | K21: =H21/SUMIF($B$18:$B$35,$B21,$H$18:$H$35)
B22: Step 03 | C22: SEC-05 | D22: Competitor Coverage Matrix | E22: =COUNTIFS(Tree!$B$2:$B$170,$C22,Tree!$E$2:$E$170,1) | F22: =COUNTIFS(Tree!$B$2:$B$170,$C22,Tree!$E$2:$E$170,2) | G22: =COUNTIFS(Tree!$B$2:$B$170,$C22,Tree!$E$2:$E$170,3) | H22: =E22+F22+G22 | I22: =COUNTIF('Allowed values'!$E$2:$E$195,$C22) | J22: =COUNTIFS(Tree!$B$2:$B$170,$C22,Tree!$E$2:$E$170,3,Tree!$J$2:$J$170,"atomic") | K22: =H22/SUMIF($B$18:$B$35,$B22,$H$18:$H$35)
B23: Step 03 | C23: SEC-06 | D23: Requirement Trace | E23: =COUNTIFS(Tree!$B$2:$B$170,$C23,Tree!$E$2:$E$170,1) | F23: =COUNTIFS(Tree!$B$2:$B$170,$C23,Tree!$E$2:$E$170,2) | G23: =COUNTIFS(Tree!$B$2:$B$170,$C23,Tree!$E$2:$E$170,3) | H23: =E23+F23+G23 | I23: =COUNTIF('Allowed values'!$E$2:$E$195,$C23) | J23: =COUNTIFS(Tree!$B$2:$B$170,$C23,Tree!$E$2:$E$170,3,Tree!$J$2:$J$170,"atomic") | K23: =H23/SUMIF($B$18:$B$35,$B23,$H$18:$H$35)
B24: Step 03 | C24: SEC-07 | D24: Competitor Gaps | E24: =COUNTIFS(Tree!$B$2:$B$170,$C24,Tree!$E$2:$E$170,1) | F24: =COUNTIFS(Tree!$B$2:$B$170,$C24,Tree!$E$2:$E$170,2) | G24: =COUNTIFS(Tree!$B$2:$B$170,$C24,Tree!$E$2:$E$170,3) | H24: =E24+F24+G24 | I24: =COUNTIF('Allowed values'!$E$2:$E$195,$C24) | J24: =COUNTIFS(Tree!$B$2:$B$170,$C24,Tree!$E$2:$E$170,3,Tree!$J$2:$J$170,"atomic") | K24: =H24/SUMIF($B$18:$B$35,$B24,$H$18:$H$35)
B25: Step 03 | C25: SEC-08 | D25: Review Log | E25: =COUNTIFS(Tree!$B$2:$B$170,$C25,Tree!$E$2:$E$170,1) | F25: =COUNTIFS(Tree!$B$2:$B$170,$C25,Tree!$E$2:$E$170,2) | G25: =COUNTIFS(Tree!$B$2:$B$170,$C25,Tree!$E$2:$E$170,3) | H25: =E25+F25+G25 | I25: =COUNTIF('Allowed values'!$E$2:$E$195,$C25) | J25: =COUNTIFS(Tree!$B$2:$B$170,$C25,Tree!$E$2:$E$170,3,Tree!$J$2:$J$170,"atomic") | K25: =H25/SUMIF($B$18:$B$35,$B25,$H$18:$H$35)
B26: Step 04 | C26: SEC-09 | D26: NFR Identity | E26: =COUNTIFS(Tree!$B$2:$B$170,$C26,Tree!$E$2:$E$170,1) | F26: =COUNTIFS(Tree!$B$2:$B$170,$C26,Tree!$E$2:$E$170,2) | G26: =COUNTIFS(Tree!$B$2:$B$170,$C26,Tree!$E$2:$E$170,3) | H26: =E26+F26+G26 | I26: =COUNTIF('Allowed values'!$E$2:$E$195,$C26) | J26: =COUNTIFS(Tree!$B$2:$B$170,$C26,Tree!$E$2:$E$170,3,Tree!$J$2:$J$170,"atomic") | K26: =H26/SUMIF($B$18:$B$35,$B26,$H$18:$H$35)
B27: Step 04 | C27: SEC-10 | D27: NFR Target | E27: =COUNTIFS(Tree!$B$2:$B$170,$C27,Tree!$E$2:$E$170,1) | F27: =COUNTIFS(Tree!$B$2:$B$170,$C27,Tree!$E$2:$E$170,2) | G27: =COUNTIFS(Tree!$B$2:$B$170,$C27,Tree!$E$2:$E$170,3) | H27: =E27+F27+G27 | I27: =COUNTIF('Allowed values'!$E$2:$E$195,$C27) | J27: =COUNTIFS(Tree!$B$2:$B$170,$C27,Tree!$E$2:$E$170,3,Tree!$J$2:$J$170,"atomic") | K27: =H27/SUMIF($B$18:$B$35,$B27,$H$18:$H$35)
B28: Step 04 | C28: SEC-11 | D28: NFR Measurement | E28: =COUNTIFS(Tree!$B$2:$B$170,$C28,Tree!$E$2:$E$170,1) | F28: =COUNTIFS(Tree!$B$2:$B$170,$C28,Tree!$E$2:$E$170,2) | G28: =COUNTIFS(Tree!$B$2:$B$170,$C28,Tree!$E$2:$E$170,3) | H28: =E28+F28+G28 | I28: =COUNTIF('Allowed values'!$E$2:$E$195,$C28) | J28: =COUNTIFS(Tree!$B$2:$B$170,$C28,Tree!$E$2:$E$170,3,Tree!$J$2:$J$170,"atomic") | K28: =H28/SUMIF($B$18:$B$35,$B28,$H$18:$H$35)
B29: Step 04 | C29: SEC-12 | D29: NFR Basis | E29: =COUNTIFS(Tree!$B$2:$B$170,$C29,Tree!$E$2:$E$170,1) | F29: =COUNTIFS(Tree!$B$2:$B$170,$C29,Tree!$E$2:$E$170,2) | G29: =COUNTIFS(Tree!$B$2:$B$170,$C29,Tree!$E$2:$E$170,3) | H29: =E29+F29+G29 | I29: =COUNTIF('Allowed values'!$E$2:$E$195,$C29) | J29: =COUNTIFS(Tree!$B$2:$B$170,$C29,Tree!$E$2:$E$170,3,Tree!$J$2:$J$170,"atomic") | K29: =H29/SUMIF($B$18:$B$35,$B29,$H$18:$H$35)
... B35: Step 01 | C35: SEC-18 | D35: Scope Lines | E35: =COUNTIFS(Tree!$B$2:$B$170,$C35,Tree!$E$2:$E$170,1) | F35: =COUNTIFS(Tree!$B$2:$B$170,$C35,Tree!$E$2:$E$170,2) | G35: =COUNTIFS(Tree!$B$2:$B$170,$C35,Tree!$E$2:$E$170,3) | H35: =E35+F35+G35 | I35: =COUNTIF('Allowed values'!$E$2:$E$195,$C35) | J35: =COUNTIFS(Tree!$B$2:$B$170,$C35,Tree!$E$2:$E$170,3,Tree!$J$2:$J$170,"atomic") | K35: =H35/SUMIF($B$18:$B$35,$B35,$H$18:$H$35)
B36: Total | D36: All sections | E36: =SUM(E18:E35) | F36: =SUM(F18:F35) | G36: =SUM(G18:G35) | H36: =SUM(H18:H35) | I36: =SUM(I18:I35) | J36: =SUM(J18:J35)
B37: Other | D37: Shared lists (no section) | I37: =COUNTIF('Allowed values'!$E$2:$E$195,"Shared")
B39: The three deliverables for each step
B40: Step | C40: Deliverable | D40: Where it is | H40: Status
B41: 01 a | C41: Output schema definition | D41: Tree (sections 14-18), Schema register, Allowed values | H41: Done: 18 sub-parameters in two tables
B42: 01 b | C42: Schema rating scorecard | D42: Scorecard (covers the whole tree); Playbook map has the Step 01 data checks | H42: Part A done; reviewer rating pending
B43: 01 c | C43: Output document | D43: Requirements (108 FRs), Scope lines | H43: ="Draft. Playbook checks: "&COUNTIF('Playbook map'!$I$34:$I$42,"PASS")&" of 7 pass"
B44: 03 a | C44: Output schema definition | D44: Tree (sections 1-8), Schema register, Allowed values | H44: Done: v1.3
B45: 03 b | C45: Schema rating scorecard | D45: Scorecard (Part A live; Part B for a reviewer) | H45: Part A done; reviewer rating pending
B46: 03 c | C46: Output document | D46: Feature discovery, Coverage matrix, Competitors | H46: ="Draft. Playbook checks: "&COUNTIF('Playbook map'!$I$5:$I$14,"PASS")&" of 7 pass"
B47: 04 a | C47: Output schema definition | D47: Tree (sections 9-13), Schema register, Allowed values | H47: Done: 18 sub-parameters, 19 columns in the nfr table
B48: 04 b | C48: Schema rating scorecard | D48: Scorecard (covers the whole tree); Playbook map has the Step 04 data checks | H48: Part A done; reviewer rating pending
B49: 04 c | C49: Output document | D49: NFR register (20 NFRs) | H49: ="Draft. Playbook checks: "&COUNTIF('Playbook map'!$I$20:$I$26,"PASS")&" of 7 pass; 6 NFRs are proposals"

Sheet Stage 1 steps
B1: Stage 1 · Discover: the five steps
B2: From the DDD Lifecycle Detailed Playbook, page 6 ('Understand before you model'). Each step has three deliverables: a) output schema definition, b) schema rating scorecard, c) output document.
B4: Step | C4: Name | D4: Purpose | E4: Do | F4: Produce | G4: Done when | H4: Go deeper | I4: In this workbook?
B5: 01 | C5: Requirement Analysis Docket | D5: Turn the raw brief into a structured, unambiguous problem statement. | E5: Split the brief into goals, scope, out-of-scope, assumptions and open questions. Give every requirement an ID. | F5: Requirements docket: ID, statement, source, priority, ambiguity notes. | G5: Every sentence of the brief maps to a requirement ID or an explicit out-of-scope line. | H5: Turn vague words like 'fast' and 'many' into numbers. Rank open questions by design impact. | I5: YES: this workbook
B6: 02 | C6: Stakeholders, Personas and Roles | D6: Know who uses the system, who owns it and who is affected. | E6: List every human and system actor with goals, permissions and frequency of use. | F6: Persona cards and a role-permission matrix. | G6: Every requirement names at least one actor. | H6: Include edge actors: auditors, support staff, regulators, scheduled jobs. | I6: No
B7: 03 | C7: Feature Discovery | D7: Find what the product must do and what market leaders already do. | E7: Study at least three competing products. Classify features as must-have, should-have or differentiator. | F7: Feature inventory with a competitor coverage matrix. | G7: Every feature traces to a requirement or is flagged as a new insight. | H7: Find what competitors lack and argue why it matters. | I7: YES: this workbook
B8: 04 | C8: NFR Discovery | D8: Fix measurable quality targets before the design locks them out. | E8: Set targets for scale, response time, availability, security, privacy, compliance and accessibility. | F8: NFR register: ID, metric, target, how it is measured. | G8: Every NFR has a number and a test method. | H8: Derive targets from volumes, not guesses. Name the regulations that apply, such as the DPDP Act 2023. | I8: YES: this workbook
B9: 05 | C9: Business Workflow Analysis | D9: Map how work actually flows from end to end. | E9: For each core workflow record trigger, steps, actors, decisions, exceptions and outputs. | F9: Workflow diagrams and an exception catalogue. | G9: Every must-have feature appears in at least one workflow. | H9: Map cancel, refund, retry and timeout paths, not only the happy path. | I9: No
B11: Exit gate G1 · Problem understood: every requirement has an ID and an actor. Every NFR has a numeric target. Every must-have feature appears in a workflow.
B13: Deliverables per step
B14: Step | C14: Name | D14: a) Output schema definition | E14: b) Schema rating scorecard | F14: c) Output document
B15: 01 | C15: Requirement Analysis Docket | D15: Tree sections 14-18, Schema register, Allowed values | E15: Scorecard | F15: Requirements, Scope lines
B16: 02 | C16: Stakeholders, Personas and Roles | D16: Not in this workbook | E16: Not in this workbook | F16: Not in this workbook
B17: 03 | C17: Feature Discovery | D17: Tree sections 1-8, Schema register, Allowed values | E17: Scorecard | F17: Feature discovery, Coverage matrix, Competitors
B18: 04 | C18: NFR Discovery | D18: Tree sections 9-13, Schema register, Allowed values | E18: Scorecard | F18: NFR register
B19: 05 | C19: Business Workflow Analysis | D19: Not in this workbook | E19: Not in this workbook | F19: Not in this workbook

Sheet Playbook map
B1: Step 03 playbook map
B2: Each phrase of the Step 03 row, the section that answers it, how many parameters sit under it (live) and a live check where the data allows one.
B4: Playbook column | C4: Playbook words | D4: Section ID | E4: Section | F4: Parameters (L2+L3) | G4: Live check | H4: Value | I4: Result
B5: Purpose | C5: Find what the product must do | D5: SEC-03 | E5: =INDEX(Tree!$C$2:$C$170,MATCH(D5,Tree!$B$2:$B$170,0)) | F5: =COUNTIFS(Tree!$B$2:$B$170,D5,Tree!$E$2:$E$170,2)+COUNTIFS(Tree!$B$2:$B$170,D5,Tree!$E$2:$E$170,3) | G5: Features recorded (one row each) | H5: =COUNTA('Feature discovery'!$A$4:$A$179) | I5: =IF(H5>=1,"PASS","FAIL")
B6: Purpose | C6: ...and what market leaders already do | D6: SEC-05 | E6: =INDEX(Tree!$C$2:$C$170,MATCH(D6,Tree!$B$2:$B$170,0)) | F6: =COUNTIFS(Tree!$B$2:$B$170,D6,Tree!$E$2:$E$170,2)+COUNTIFS(Tree!$B$2:$B$170,D6,Tree!$E$2:$E$170,3) | G6: Features with a coverage row | H6: =COUNTA('Coverage matrix'!$A$4:$A$126) | I6: =IF(H6>=1,"PASS","FAIL")
B7: Do | C7: Study at least three competing products | D7: SEC-02 | E7: =INDEX(Tree!$C$2:$C$170,MATCH(D7,Tree!$B$2:$B$170,0)) | F7: =COUNTIFS(Tree!$B$2:$B$170,D7,Tree!$E$2:$E$170,2)+COUNTIFS(Tree!$B$2:$B$170,D7,Tree!$E$2:$E$170,3) | G7: Competitors studied (needs 3 or more) | H7: =COUNTA(Competitors!$A$4:$A$7) | I7: =IF(H7>=3,"PASS","FAIL")
B8: Do | C8: Classify features as must-have, should-have or differentiator | D8: SEC-04 | E8: =INDEX(Tree!$C$2:$C$170,MATCH(D8,Tree!$B$2:$B$170,0)) | F8: =COUNTIFS(Tree!$B$2:$B$170,D8,Tree!$E$2:$E$170,2)+COUNTIFS(Tree!$B$2:$B$170,D8,Tree!$E$2:$E$170,3) | G8: Features with a class other than the three (needs 0) | H8: =COUNTA('Feature discovery'!$K$4:$K$179)-COUNTIF('Feature discovery'!$K$4:$K$179,"MUST-HAVE")-COUNTIF('Feature discovery'!$K$4:$K$179,"SHOULD-HAVE")-COUNTIF('Feature discovery'!$K$4:$K$179,"DIFFERENTIATOR") | I8: =IF(H8=0,"PASS","FAIL")
B9: Produce | C9: Feature inventory ... | D9: SEC-03 | E9: =INDEX(Tree!$C$2:$C$170,MATCH(D9,Tree!$B$2:$B$170,0)) | F9: =COUNTIFS(Tree!$B$2:$B$170,D9,Tree!$E$2:$E$170,2)+COUNTIFS(Tree!$B$2:$B$170,D9,Tree!$E$2:$E$170,3) | G9: Feature discovery rows | H9: =COUNTA('Feature discovery'!$A$4:$A$179) | I9: =IF(H9>=1,"PASS","FAIL")
B10: Produce | C10: ... with a competitor coverage matrix | D10: SEC-05 | E10: =INDEX(Tree!$C$2:$C$170,MATCH(D10,Tree!$B$2:$B$170,0)) | F10: =COUNTIFS(Tree!$B$2:$B$170,D10,Tree!$E$2:$E$170,2)+COUNTIFS(Tree!$B$2:$B$170,D10,Tree!$E$2:$E$170,3) | G10: Coverage matrix rows | H10: =COUNTA('Coverage matrix'!$A$4:$A$126) | I10: =IF(H10>=1,"PASS","FAIL")
B11: Done when | C11: Every feature traces to a requirement or is flagged as a new insight | D11: SEC-06 | E11: =INDEX(Tree!$C$2:$C$170,MATCH(D11,Tree!$B$2:$B$170,0)) | F11: =COUNTIFS(Tree!$B$2:$B$170,D11,Tree!$E$2:$E$170,2)+COUNTIFS(Tree!$B$2:$B$170,D11,Tree!$E$2:$E$170,3) | G11: Features with neither (needs 0) | H11: =COUNTA('Feature discovery'!$A$4:$A$179)-COUNTIF('Feature discovery'!$S$4:$S$179,"Traced*")-COUNTIF('Feature discovery'!$S$4:$S$179,"NEW INSIGHT") | I11: =IF(H11=0,"PASS","FAIL")
B12: Go deeper | C12: Find what competitors lack and argue why it matters | D12: SEC-07 | E12: =INDEX(Tree!$C$2:$C$170,MATCH(D12,Tree!$B$2:$B$170,0)) | F12: =COUNTIFS(Tree!$B$2:$B$170,D12,Tree!$E$2:$E$170,2)+COUNTIFS(Tree!$B$2:$B$170,D12,Tree!$E$2:$E$170,3) | G12: Not checked by a formula: needs a person to judge the arguments | I12: person
B13: Not in the playbook row | C13: Context of the study (product, method, version, date) | D13: SEC-01 | E13: =INDEX(Tree!$C$2:$C$170,MATCH(D13,Tree!$B$2:$B$170,0)) | F13: =COUNTIFS(Tree!$B$2:$B$170,D13,Tree!$E$2:$E$170,2)+COUNTIFS(Tree!$B$2:$B$170,D13,Tree!$E$2:$E$170,3) | G13: Added so the study can be repeated | I13: person
B14: Not in the playbook row | C14: Review, review, review loop (Subramanian's transcript) | D14: SEC-08 | E14: =INDEX(Tree!$C$2:$C$170,MATCH(D14,Tree!$B$2:$B$170,0)) | F14: =COUNTIFS(Tree!$B$2:$B$170,D14,Tree!$E$2:$E$170,2)+COUNTIFS(Tree!$B$2:$B$170,D14,Tree!$E$2:$E$170,3) | G14: Added from the transcript | I14: person
B17: The checks read the Feature discovery, Coverage matrix and Competitors sheets, so they test the data, not just the schema.
B18: Step 04 NFR Discovery: playbook map
B19: Playbook column | C19: Playbook words | D19: Section ID | E19: Section | F19: Parameters (L2+L3) | G19: Live check | H19: Value | I19: Result
B20: Purpose | C20: Fix measurable quality targets before the design locks them out | D20: SEC-10 | E20: =INDEX(Tree!$C$2:$C$170,MATCH(D20,Tree!$B$2:$B$170,0)) | F20: =COUNTIFS(Tree!$B$2:$B$170,D20,Tree!$E$2:$E$170,2)+COUNTIFS(Tree!$B$2:$B$170,D20,Tree!$E$2:$E$170,3) | G20: Approved NFRs with a target recorded (needs 1 or more) | H20: =COUNTIFS('NFR register'!$K$4:$K$29,"Set",'NFR register'!$R$4:$R$29,"<>Proposed") | I20: =IF(H20>=1,"PASS","FAIL")
B21: Do | C21: Set targets for scale, response time, availability, security, privacy, compliance and accessibility | D21: SEC-09 | E21: =INDEX(Tree!$C$2:$C$170,MATCH(D21,Tree!$B$2:$B$170,0)) | F21: =COUNTIFS(Tree!$B$2:$B$170,D21,Tree!$E$2:$E$170,2)+COUNTIFS(Tree!$B$2:$B$170,D21,Tree!$E$2:$E$170,3) | G21: Of those 7 areas, how many have no approved NFR (needs 0) | H21: =(COUNTIFS('NFR register'!$C$4:$C$29,"Scale",'NFR register'!$R$4:$R$29,"<>Proposed")=0)+(COUNTIFS('NFR register'!$C$4:$C$29,"Performance",'NFR register'!$R$4:$R$29,"<>Proposed")=0)+(COUNTIFS('NFR register'!$C$4:$C$29,"Availability and recovery",'NFR register'!$R$4:$R$29,"<>Proposed")=0)+(COUNTIFS('NFR register'!$C$4:$C$29,"Security",'NFR register'!$R$4:$R$29,"<>Proposed")=0)+(COUNTIFS('NFR register'!$C$4:$C$29,"Privacy",'NFR register'!$R$4:$R$29,"<>Proposed")=0)+(COUNTIFS('NFR register'!$C$4:$C$29,"Compliance",'NFR register'!$R$4:$R$29,"<>Proposed")=0)+(COUNTIFS('NFR register'!$C$4:$C$29,"Accessibility",'NFR register'!$R$4:$R$29,"<>Proposed")=0) | I21: =IF(H21=0,"PASS","FAIL")
B22: Produce | C22: NFR register: ID, metric, target, how it is measured | D22: SEC-11 | E22: =INDEX(Tree!$C$2:$C$170,MATCH(D22,Tree!$B$2:$B$170,0)) | F22: =COUNTIFS(Tree!$B$2:$B$170,D22,Tree!$E$2:$E$170,2)+COUNTIFS(Tree!$B$2:$B$170,D22,Tree!$E$2:$E$170,3) | G22: Approved NFRs in the register | H22: =COUNTIFS('NFR register'!$R$4:$R$29,"<>Proposed") | I22: =IF(H22>=1,"PASS","FAIL")
B23: Done when | C23: Every NFR has a number ... | D23: SEC-10 | E23: =INDEX(Tree!$C$2:$C$170,MATCH(D23,Tree!$B$2:$B$170,0)) | F23: =COUNTIFS(Tree!$B$2:$B$170,D23,Tree!$E$2:$E$170,2)+COUNTIFS(Tree!$B$2:$B$170,D23,Tree!$E$2:$E$170,3) | G23: Approved NFRs without a numeric target (needs 0) | H23: =COUNTIFS('NFR register'!$R$4:$R$29,"<>Proposed")-COUNTIFS('NFR register'!$I$4:$I$29,"<>",'NFR register'!$R$4:$R$29,"<>Proposed") | I23: =IF(H23=0,"PASS","FAIL")
B24: Done when | C24: ... and a test method | D24: SEC-11 | E24: =INDEX(Tree!$C$2:$C$170,MATCH(D24,Tree!$B$2:$B$170,0)) | F24: =COUNTIFS(Tree!$B$2:$B$170,D24,Tree!$E$2:$E$170,2)+COUNTIFS(Tree!$B$2:$B$170,D24,Tree!$E$2:$E$170,3) | G24: Approved NFRs without a test method (needs 0) | H24: =COUNTIFS('NFR register'!$M$4:$M$29,"Not yet defined",'NFR register'!$R$4:$R$29,"<>Proposed") | I24: =IF(H24=0,"PASS","FAIL")
B25: Go deeper | C25: Derive targets from volumes, not guesses | D25: SEC-12 | E25: =INDEX(Tree!$C$2:$C$170,MATCH(D25,Tree!$B$2:$B$170,0)) | F25: =COUNTIFS(Tree!$B$2:$B$170,D25,Tree!$E$2:$E$170,2)+COUNTIFS(Tree!$B$2:$B$170,D25,Tree!$E$2:$E$170,3) | G25: Approved NFRs with no derivation recorded (needs 0) | H25: =COUNTIFS('NFR register'!$O$4:$O$29,"Not yet derived",'NFR register'!$R$4:$R$29,"<>Proposed") | I25: =IF(H25=0,"PASS","FAIL")
B26: Go deeper | C26: Name the regulations that apply, such as the DPDP Act 2023 | D26: SEC-12 | E26: =INDEX(Tree!$C$2:$C$170,MATCH(D26,Tree!$B$2:$B$170,0)) | F26: =COUNTIFS(Tree!$B$2:$B$170,D26,Tree!$E$2:$E$170,2)+COUNTIFS(Tree!$B$2:$B$170,D26,Tree!$E$2:$E$170,3) | G26: Approved NFRs that name a regulation (needs 1 or more) | H26: =COUNTIFS('NFR register'!$Q$4:$Q$29,"?*",'NFR register'!$R$4:$R$29,"<>Proposed") | I26: =IF(H26>=1,"PASS","FAIL")
B30: Step 04 results are meant to show the gaps: a FAIL here is something still to fix in the NFR register, not a fault in the schema.
B32: Step 01 Requirement Analysis Docket: playbook map
B33: Playbook column | C33: Playbook words | D33: Section ID | E33: Section | F33: Parameters (L2+L3) | G33: Live check | H33: Value | I33: Result
B34: Purpose | C34: Turn the raw brief into a structured, unambiguous problem statement | D34: SEC-14 | E34: =INDEX(Tree!$C$2:$C$170,MATCH(D34,Tree!$B$2:$B$170,0)) | F34: =COUNTIFS(Tree!$B$2:$B$170,D34,Tree!$E$2:$E$170,2)+COUNTIFS(Tree!$B$2:$B$170,D34,Tree!$E$2:$E$170,3) | G34: Requirements recorded (needs 1 or more) | H34: =COUNTA('Requirements'!$A$4:$A$111) | I34: =IF(H34>=1,"PASS","FAIL")
B35: Do | C35: Split the brief into goals, scope, out-of-scope, assumptions and open questions | D35: SEC-18 | E35: =INDEX(Tree!$C$2:$C$170,MATCH(D35,Tree!$B$2:$B$170,0)) | F35: =COUNTIFS(Tree!$B$2:$B$170,D35,Tree!$E$2:$E$170,2)+COUNTIFS(Tree!$B$2:$B$170,D35,Tree!$E$2:$E$170,3) | G35: Of those 5 line types, how many have no line (needs 0) | H35: =(COUNTIF('Scope lines'!$C$4:$C$22,"Goal")=0)+(COUNTIF('Scope lines'!$C$4:$C$22,"In scope")=0)+(COUNTIF('Scope lines'!$C$4:$C$22,"Out of scope")=0)+(COUNTIF('Scope lines'!$C$4:$C$22,"Assumption")=0)+(COUNTIF('Scope lines'!$C$4:$C$22,"Open question")=0) | I35: =IF(H35=0,"PASS","FAIL")
B36: Do | C36: Give every requirement an ID | D36: SEC-14 | E36: =INDEX(Tree!$C$2:$C$170,MATCH(D36,Tree!$B$2:$B$170,0)) | F36: =COUNTIFS(Tree!$B$2:$B$170,D36,Tree!$E$2:$E$170,2)+COUNTIFS(Tree!$B$2:$B$170,D36,Tree!$E$2:$E$170,3) | G36: Requirements with no ID or a repeated ID (needs 0) | H36: =COUNTA('Requirements'!$D$4:$D$111)-COUNTA('Requirements'!$A$4:$A$111)+SUMPRODUCT(--(COUNTIF('Requirements'!$A$4:$A$111,'Requirements'!$A$4:$A$111)>1)) | I36: =IF(H36=0,"PASS","FAIL")
B37: Produce | C37: Requirements docket: ID, statement, source ... | D37: SEC-15 | E37: =INDEX(Tree!$C$2:$C$170,MATCH(D37,Tree!$B$2:$B$170,0)) | F37: =COUNTIFS(Tree!$B$2:$B$170,D37,Tree!$E$2:$E$170,2)+COUNTIFS(Tree!$B$2:$B$170,D37,Tree!$E$2:$E$170,3) | G37: Requirements with no source recorded (needs 0) | H37: =COUNTA('Requirements'!$A$4:$A$111)-COUNTIFS('Requirements'!$E$4:$E$111,"<>Not recorded",'Requirements'!$E$4:$E$111,"<>") | I37: =IF(H37=0,"PASS","FAIL")
B38: Produce | C38: ... priority ... | D38: SEC-16 | E38: =INDEX(Tree!$C$2:$C$170,MATCH(D38,Tree!$B$2:$B$170,0)) | F38: =COUNTIFS(Tree!$B$2:$B$170,D38,Tree!$E$2:$E$170,2)+COUNTIFS(Tree!$B$2:$B$170,D38,Tree!$E$2:$E$170,3) | G38: Requirements with no priority (needs 0) | H38: =COUNTA('Requirements'!$A$4:$A$111)-COUNTA('Requirements'!$H$4:$H$111) | I38: =IF(H38=0,"PASS","FAIL")
B39: Produce | C39: ... ambiguity notes | D39: SEC-16 | E39: =INDEX(Tree!$C$2:$C$170,MATCH(D39,Tree!$B$2:$B$170,0)) | F39: =COUNTIFS(Tree!$B$2:$B$170,D39,Tree!$E$2:$E$170,2)+COUNTIFS(Tree!$B$2:$B$170,D39,Tree!$E$2:$E$170,3) | G39: Requirements with an ambiguity note (information only) | H39: =COUNTA('Requirements'!$J$4:$J$111) | I39: info
B40: Done when | C40: Every sentence of the brief maps to a requirement ID or an explicit out-of-scope line | D40: SEC-18 | E40: =INDEX(Tree!$C$2:$C$170,MATCH(D40,Tree!$B$2:$B$170,0)) | F40: =COUNTIFS(Tree!$B$2:$B$170,D40,Tree!$E$2:$E$170,2)+COUNTIFS(Tree!$B$2:$B$170,D40,Tree!$E$2:$E$170,3) | G40: Needs the original brief: a person checks | I40: person
B41: Exit gate G1 | C41: Every requirement has an ID and an actor | D41: SEC-15 | E41: =INDEX(Tree!$C$2:$C$170,MATCH(D41,Tree!$B$2:$B$170,0)) | F41: =COUNTIFS(Tree!$B$2:$B$170,D41,Tree!$E$2:$E$170,2)+COUNTIFS(Tree!$B$2:$B$170,D41,Tree!$E$2:$E$170,3) | G41: Requirements with no actor (needs 0) | H41: =COUNTA('Requirements'!$A$4:$A$111)-COUNTA('Requirements'!$G$4:$G$111) | I41: =IF(H41=0,"PASS","FAIL")
B42: Go deeper | C42: Rank open questions by design impact | D42: SEC-18 | E42: =INDEX(Tree!$C$2:$C$170,MATCH(D42,Tree!$B$2:$B$170,0)) | F42: =COUNTIFS(Tree!$B$2:$B$170,D42,Tree!$E$2:$E$170,2)+COUNTIFS(Tree!$B$2:$B$170,D42,Tree!$E$2:$E$170,3) | G42: Open questions recorded (needs 1 or more; the ranking itself is not recorded) | H42: =COUNTIF('Scope lines'!$C$4:$C$22,"Open question") | I42: =IF(H42>=1,"PASS","FAIL")
B44: Step 01 results are meant to show the gaps: source and brief mapping need the original brief.

Sheet Tree
A1: Deliverable | B1: Section ID | C1: Section | D1: Path id | E1: Level | F1: Level name | G1: Name | H1: Definition | I1: Data type | J1: Atomic or derived | K1: Required | L1: Allowed values | M1: Example | N1: Table | O1: Column
A2: Step 03 | B2: SEC-01 | C2: Study Frame | D2: 1 | E2: 1 | F2: Macro | G2: Study Frame | H2: Which product the study is about and how the study was done, so it can be repeated. | N2: study
A3: Step 03 | B3: SEC-01 | C3: Study Frame | D3: 1.1 | E3: 2 | F3: Micro | G3: Study identity | H3: Which product and which analysis stage this study belongs to. | N3: study | O3: (3 columns)
A4: Step 03 | B4: SEC-01 | C4: Study Frame | D4: 1.1.1 | E4: 3 | F4: Nano | G4: Study id | H4: One short code for this study. | I4: id | J4: atomic | K4: required | L4: unique, pattern FDS-nn | M4: FDS-01 | N4: study | O4: study_id
A5: Step 03 | B5: SEC-01 | C5: Study Frame | D5: 1.1.2 | E5: 3 | F5: Nano | G5: Product name | H5: The product the features are discovered for. | I5: text | J5: atomic | K5: required | L5: 1 to 100 characters | M5: Talentra | N5: study | O5: product_name
A6: Step 03 | B6: SEC-01 | C6: Study Frame | D6: 1.1.3 | E6: 3 | F6: Nano | G6: Stage | H6: Which analysis stage this study is. | I6: enum | J6: atomic | K6: required | L6: list: Stage | M6: 03 Feature discovery | N6: study | O6: stage
A7: Step 03 | B7: SEC-01 | C7: Study Frame | D7: 1.2 | E7: 2 | F7: Micro | G7: Study method | H7: How the discovery was done. | N7: study | O7: (3 columns)
A8: Step 03 | B8: SEC-01 | C8: Study Frame | D8: 1.2.1 | E8: 3 | F8: Nano | G8: Method type | H8: Whether people, one LLM or several LLMs did the discovery. | I8: enum | J8: atomic | K8: required | L8: list: MethodType | M8: LLM assisted | N8: study | O8: method_type
A9: Step 03 | B9: SEC-01 | C9: Study Frame | D9: 1.2.2 | E9: 3 | F9: Nano | G9: Schema version | H9: The frozen version of this schema that the study follows. | I9: text | J9: atomic | K9: required | L9: pattern n.n | M9: 1.0 | N9: study | O9: schema_version
A10: Step 03 | B10: SEC-01 | C10: Study Frame | D10: 1.2.3 | E10: 3 | F10: Nano | G10: Study date | H10: The day the study was recorded. | I10: date | J10: atomic | K10: required | L10: date, not in the future | M10: 2026-10-21 | N10: study | O10: study_date
A11: Step 03 | B11: SEC-02 | C11: Competitors Studied | D11: 2 | E11: 1 | F11: Macro | G11: Competitors Studied | H11: The products we compare with. The gate needs at least three of them. | N11: competitor
A12: Step 03 | B12: SEC-02 | C12: Competitors Studied | D12: 2.1 | E12: 2 | F12: Micro | G12: Competitor identity | H12: Which product it is and how much weight its answers carry. | N12: competitor | O12: (4 columns)
A13: Step 03 | B13: SEC-02 | C13: Competitors Studied | D13: 2.1.1 | E13: 3 | F13: Nano | G13: Competitor id | H13: One short code for the competitor. | I13: id | J13: atomic | K13: required | L13: unique, pattern COMP-nn | M13: COMP-03 | N13: competitor | O13: competitor_id
A14: Step 03 | B14: SEC-02 | C14: Competitors Studied | D14: 2.1.2 | E14: 3 | F14: Nano | G14: Competitor name | H14: The name of the competing product. | I14: text | J14: atomic | K14: required | L14: 1 to 100 characters | M14: LinkedIn | N14: competitor | O14: competitor_name
A15: Step 03 | B15: SEC-02 | C15: Competitors Studied | D15: 2.1.3 | E15: 3 | F15: Nano | G15: Product type | H15: What kind of product it is. | I15: enum | J15: atomic | K15: required | L15: list: ProductType | M15: Professional network | N15: competitor | O15: product_type
A16: Step 03 | B16: SEC-02 | C16: Competitors Studied | D16: 2.1.4 | E16: 3 | F16: Nano | G16: Tier | H16: Leader, specialist or reference; only leaders count in the classification rule. | I16: enum | J16: atomic | K16: required | L16: list: Tier | M16: Leader | N16: competitor | O16: tier
A17: Step 03 | B17: SEC-02 | C17: Competitors Studied | D17: 2.2 | E17: 2 | F17: Micro | G17: Study scope | H17: How much of the competitor was studied. | N17: competitor | O17: (3 columns)
A18: Step 03 | B18: SEC-02 | C18: Competitors Studied | D18: 2.2.1 | E18: 3 | F18: Nano | G18: Scope | H18: Whether the competitor is compared for general features or campus features only. | I18: enum | J18: atomic | K18: required | L18: list: StudyScope | M18: General | N18: competitor | O18: study_scope
A19: Step 03 | B19: SEC-02 | C19: Competitors Studied | D19: 2.2.2 | E19: 3 | F19: Nano | G19: Pages studied | H19: How many pages of the competitor were read. | I19: integer | J19: atomic | K19: required | L19: 0 or more | M19: 14 | N19: competitor | O19: pages_studied
A20: Step 03 | B20: SEC-02 | C20: Competitors Studied | D20: 2.2.3 | E20: 3 | F20: Nano | G20: Access level | H20: Whether the pages could be read in full, only as a search summary, or not at all. | I20: enum | J20: atomic | K20: required | L20: list: PageAccess | M20: Read | N20: competitor | O20: access_level
A21: Step 03 | B21: SEC-02 | C21: Competitors Studied | D21: 2.3 | E21: 2 | F21: Micro | G21: Verification | H21: How sure we are about what we know of this competitor. | N21: competitor | O21: (2 columns)
A22: Step 03 | B22: SEC-02 | C22: Competitors Studied | D22: 2.3.1 | E22: 3 | F22: Nano | G22: Last checked on | H22: The day someone last checked the competitor's live pages. | I22: date | J22: atomic | K22: optional | L22: date, not in the future | M22: 2026-10-16 | N22: competitor | O22: last_checked_on
A23: Step 03 | B23: SEC-02 | C23: Competitors Studied | D23: 2.3.2 | E23: 3 | F23: Nano | G23: Evidence status | H23: Public if read on a live page, Known if only recorded in our register. | I23: enum | J23: atomic | K23: required | L23: list: EvidenceStatus | M23: Public | N23: competitor | O23: evidence_status
A24: Step 03 | B24: SEC-03 | C24: Feature Inventory | D24: 3 | E24: 1 | F24: Macro | G24: Feature Inventory | H24: Everything the product must do: one row per feature or per capability inside a feature. | N24: feature
A25: Step 03 | B25: SEC-03 | C25: Feature Inventory | D25: 3.1 | E25: 2 | F25: Micro | G25: Feature identity | H25: Which feature it is and where it sits. | N25: feature | O25: (4 columns)
A26: Step 03 | B26: SEC-03 | C26: Feature Inventory | D26: 3.1.1 | E26: 3 | F26: Nano | G26: Feature id | H26: One fixed code for the feature. | I26: id | J26: atomic | K26: required | L26: unique, pattern FD-nnn | M26: FD-001 | N26: feature | O26: feature_id
A27: Step 03 | B27: SEC-03 | C27: Feature Inventory | D27: 3.1.2 | E27: 3 | F27: Nano | G27: Feature name | H27: A short name in plain words. | I27: text | J27: atomic | K27: required | L27: 1 to 150 characters, unique | M27: Resume headline and profile summary | N27: feature | O27: feature_name
A28: Step 03 | B28: SEC-03 | C28: Feature Inventory | D28: 3.1.3 | E28: 3 | F28: Nano | G28: Feature level | H28: Feature, or capability (one smaller requirement inside a feature). | I28: enum | J28: atomic | K28: required | L28: list: FeatureLevel | M28: Feature | N28: feature | O28: feature_level
A29: Step 03 | B29: SEC-03 | C29: Feature Inventory | D29: 3.1.4 | E29: 3 | F29: Nano | G29: Parent feature id | H29: For a capability, the feature it belongs to. | I29: reference | J29: atomic | K29: conditional | L29: an existing feature_id; required when level is Capability | M29: FD-012 | N29: feature | O29: parent_feature_id
A30: Step 03 | B30: SEC-03 | C30: Feature Inventory | D30: 3.2 | E30: 2 | F30: Micro | G30: Description | H30: What it is, for whom and where it belongs. | N30: feature | O30: (4 columns)
A31: Step 03 | B31: SEC-03 | C31: Feature Inventory | D31: 3.2.1 | E31: 3 | F31: Nano | G31: Plain description | H31: One or two sentences saying what the feature does. | I31: text | J31: atomic | K31: required | L31: 1 to 500 characters | M31: A short headline and a summary of the candidate | N31: feature | O31: description
A32: Step 03 | B32: SEC-03 | C32: Feature Inventory | D32: 3.2.2 | E32: 3 | F32: Nano | G32: Category | H32: The area of the product it belongs to. | I32: enum | J32: atomic | K32: required | L32: list: Category | M32: Profile | N32: feature | O32: category
A33: Step 03 | B33: SEC-03 | C33: Feature Inventory | D33: 3.2.3 | E33: 3 | F33: Nano | G33: Persona | H33: The type of person who uses it most. | I33: enum | J33: atomic | K33: required | L33: list: Persona | M33: Candidate | N33: feature | O33: persona
A34: Step 03 | B34: SEC-03 | C34: Feature Inventory | D34: 3.2.4 | E34: 3 | F34: Nano | G34: Scope | H34: General, campus only, or not observable in competitors. | I34: enum | J34: atomic | K34: required | L34: list: ComparisonScope | M34: General | N34: feature | O34: scope
A35: Step 03 | B35: SEC-03 | C35: Feature Inventory | D35: 3.3 | E35: 2 | F35: Micro | G35: Origin | H35: Where the feature was first found. | N35: feature | O35: (2 columns)
A36: Step 03 | B36: SEC-03 | C36: Feature Inventory | D36: 3.3.1 | E36: 3 | F36: Nano | G36: Source type | H36: What kind of source named the feature. | I36: enum | J36: atomic | K36: required | L36: list: SourceType | M36: Competitor register | N36: feature | O36: source_type
A37: Step 03 | B37: SEC-03 | C37: Feature Inventory | D37: 3.3.2 | E37: 3 | F37: Nano | G37: Source reference | H37: The section or row of that source. | I37: text | J37: atomic | K37: required | L37: 1 to 200 characters | M37: Section 1: Candidate profile | N37: feature | O37: source_reference
A38: Step 03 | B38: SEC-03 | C38: Feature Inventory | D38: 3.4 | E38: 2 | F38: Micro | G38: Scope decision | H38: Whether the feature stays in the product. | N38: feature | O38: (2 columns)
A39: Step 03 | B39: SEC-03 | C39: Feature Inventory | D39: 3.4.1 | E39: 3 | F39: Nano | G39: Scope decision | H39: Keep, defer or drop. | I39: enum | J39: atomic | K39: required | L39: list: ScopeDecision | M39: Keep | N39: feature | O39: scope_decision
A40: Step 03 | B40: SEC-03 | C40: Feature Inventory | D40: 3.4.2 | E40: 3 | F40: Nano | G40: Decision reason | H40: Why a feature was deferred or dropped. | I40: text | J40: atomic | K40: conditional | L40: required when the decision is not Keep | M40: Left out on purpose: placement fees belong to finance | N40: feature | O40: decision_reason
A41: Step 03 | B41: SEC-04 | C41: Feature Classification | D41: 4 | E41: 1 | F41: Macro | G41: Feature Classification | H41: Must-have, should-have or differentiator, with the rule and how sure we are. | N41: feature
A42: Step 03 | B42: SEC-04 | C42: Feature Classification | D42: 4.1 | E42: 2 | F42: Micro | G42: Class result | H42: The class and the reason for it. | N42: feature | O42: (3 columns)
A43: Step 03 | B43: SEC-04 | C43: Feature Classification | D43: 4.1.1 | E43: 3 | F43: Nano | G43: Classification | H43: MUST-HAVE, SHOULD-HAVE or DIFFERENTIATOR. | I43: enum | J43: atomic | K43: required | L43: list: Class | M43: MUST-HAVE | N43: feature | O43: classification
A44: Step 03 | B44: SEC-04 | C44: Feature Classification | D44: 4.1.2 | E44: 3 | F44: Nano | G44: Class basis | H44: The rule that gave the class. | I44: enum | J44: atomic | K44: required | L44: list: ClassBasis | M44: Competitor matrix rule | N44: feature | O44: class_basis
A45: Step 03 | B45: SEC-04 | C45: Feature Classification | D45: 4.1.3 | E45: 3 | F45: Nano | G45: Class reason | H45: One sentence of proof, for example how many leaders offer it. | I45: text | J45: atomic | K45: required | L45: 1 to 300 characters | M45: 3 of 3 studied leaders offer it | N45: feature | O45: class_reason
A46: Step 03 | B46: SEC-04 | C46: Feature Classification | D46: 4.2 | E46: 2 | F46: Micro | G46: Confidence | H46: How sure we are about the class. | N46: feature | O46: (4 columns)
A47: Step 03 | B47: SEC-04 | C47: Feature Classification | D47: 4.2.1 | E47: 3 | F47: Nano | G47: Confidence | H47: Firm, provisional or declared. | I47: enum | J47: derived | K47: required | L47: list: Confidence | M47: Firm | N47: feature | O47: confidence
A48: Step 03 | B48: SEC-04 | C48: Feature Classification | D48: 4.2.2 | E48: 3 | F48: Nano | G48: Evidence status | H48: The weakest evidence behind the coverage cells of this feature. | I48: enum | J48: derived | K48: required | L48: list: EvidenceStatus | M48: Public | N48: feature | O48: evidence_status
A49: Step 03 | B49: SEC-04 | C49: Feature Classification | D49: 4.2.3 | E49: 3 | F49: Nano | G49: Leaders studied | H49: How many leader competitors in scope have a coverage row for this feature. | I49: integer | J49: derived | K49: required | L49: 0 to number of leaders | M49: 3 | N49: feature | O49: leaders_studied
A50: Step 03 | B50: SEC-04 | C50: Feature Classification | D50: 4.2.4 | E50: 3 | F50: Nano | G50: Leaders offering | H50: How many of those leaders offer it fully or partly. | I50: integer | J50: derived | K50: required | L50: 0 to leaders studied | M50: 3 | N50: feature | O50: leaders_offering
A51: Step 03 | B51: SEC-05 | C51: Competitor Coverage Matrix | D51: 5 | E51: 1 | F51: Macro | G51: Competitor Coverage Matrix | H51: Who offers each feature, and where we stand: one row per feature and competitor. | N51: competitor_coverage, feature
A52: Step 03 | B52: SEC-05 | C52: Competitor Coverage Matrix | D52: 5.1 | E52: 2 | F52: Micro | G52: Matrix cell key | H52: Which feature and which competitor the cell is about. | N52: competitor_coverage | O52: (2 columns)
A53: Step 03 | B53: SEC-05 | C53: Competitor Coverage Matrix | D53: 5.1.1 | E53: 3 | F53: Nano | G53: Feature id | H53: The feature in this cell. | I53: reference | J53: atomic | K53: required | L53: an existing feature_id | M53: FD-001 | N53: competitor_coverage | O53: feature_id
A54: Step 03 | B54: SEC-05 | C54: Competitor Coverage Matrix | D54: 5.1.2 | E54: 3 | F54: Nano | G54: Competitor id | H54: The competitor in this cell. | I54: reference | J54: atomic | K54: required | L54: an existing competitor_id | M54: COMP-03 | N54: competitor_coverage | O54: competitor_id
A55: Step 03 | B55: SEC-05 | C55: Competitor Coverage Matrix | D55: 5.2 | E55: 2 | F55: Micro | G55: Offering | H55: Whether the competitor offers the feature. | N55: competitor_coverage | O55: (2 columns)
A56: Step 03 | B56: SEC-05 | C56: Competitor Coverage Matrix | D56: 5.2.1 | E56: 3 | F56: Nano | G56: Offering | H56: Yes, partial, no or not verified. | I56: enum | J56: atomic | K56: required | L56: list: CellValue | M56: Yes | N56: competitor_coverage | O56: offering
A57: Step 03 | B57: SEC-05 | C57: Competitor Coverage Matrix | D57: 5.2.2 | E57: 3 | F57: Nano | G57: Offering note | H57: A short note, such as a paid-plan limit. | I57: text | J57: atomic | K57: optional | L57: 0 to 300 characters | M57: Only on the paid plan | N57: competitor_coverage | O57: offering_note
A58: Step 03 | B58: SEC-05 | C58: Competitor Coverage Matrix | D58: 5.3 | E58: 2 | F58: Micro | G58: Evidence | H58: What the cell is based on. | N58: competitor_coverage | O58: (3 columns)
A59: Step 03 | B59: SEC-05 | C59: Competitor Coverage Matrix | D59: 5.3.1 | E59: 3 | F59: Nano | G59: Evidence type | H59: Page read, search summary, register text and so on. | I59: enum | J59: atomic | K59: required | L59: list: EvidenceType | M59: Page read | N59: competitor_coverage | O59: evidence_type
A60: Step 03 | B60: SEC-05 | C60: Competitor Coverage Matrix | D60: 5.3.2 | E60: 3 | F60: Nano | G60: Evidence source | H60: The page or register row. | I60: text | J60: atomic | K60: required | L60: 1 to 300 characters | M60: Naukri help page: resume headline | N60: competitor_coverage | O60: evidence_source
A61: Step 03 | B61: SEC-05 | C61: Competitor Coverage Matrix | D61: 5.3.3 | E61: 3 | F61: Nano | G61: Checked on | H61: The day the evidence was checked. | I61: date | J61: atomic | K61: optional | L61: date, not in the future | M61: 2026-10-16 | N61: competitor_coverage | O61: checked_on
A62: Step 03 | B62: SEC-05 | C62: Competitor Coverage Matrix | D62: 5.4 | E62: 2 | F62: Micro | G62: Our position | H62: How our product compares for this feature. | N62: feature | O62: (2 columns)
A63: Step 03 | B63: SEC-05 | C63: Competitor Coverage Matrix | D63: 5.4.1 | E63: 3 | F63: Nano | G63: Our coverage | H63: Built and tested, built, planned, not built or left out. | I63: enum | J63: atomic | K63: required | L63: list: OurCoverage | M63: Built and tested | N63: feature | O63: our_coverage
A64: Step 03 | B64: SEC-05 | C64: Competitor Coverage Matrix | D64: 5.4.2 | E64: 3 | F64: Nano | G64: Verdict | H64: Matches, exceeds, falls short, planned or not compared. | I64: enum | J64: atomic | K64: required | L64: list: Verdict | M64: Matches | N64: feature | O64: verdict
A65: Step 03 | B65: SEC-06 | C65: Requirement Trace | D65: 6 | E65: 1 | F65: Macro | G65: Requirement Trace | H65: Every feature traces to a requirement or is flagged as a new insight. | N65: feature_requirement, feature
A66: Step 03 | B66: SEC-06 | C66: Requirement Trace | D66: 6.1 | E66: 2 | F66: Micro | G66: Requirement link | H66: Which requirement the feature is built under. | N66: feature_requirement | O66: (3 columns)
A67: Step 03 | B67: SEC-06 | C67: Requirement Trace | D67: 6.1.1 | E67: 3 | F67: Nano | G67: Feature id | H67: The feature that is linked. | I67: reference | J67: atomic | K67: required | L67: an existing feature_id | M67: FD-001 | N67: feature_requirement | O67: feature_id
A68: Step 03 | B68: SEC-06 | C68: Requirement Trace | D68: 6.1.2 | E68: 3 | F68: Nano | G68: Requirement id | H68: The functional or non-functional requirement. | I68: text | J68: atomic | K68: required | L68: pattern FR-xxx or NFR-nn | M68: FR-P03 | N68: feature_requirement | O68: requirement_id
A69: Step 03 | B69: SEC-06 | C69: Requirement Trace | D69: 6.1.3 | E69: 3 | F69: Nano | G69: Relationship | H69: Implemented by, or only related to. | I69: enum | J69: atomic | K69: required | L69: list: Relationship | M69: Implemented by | N69: feature_requirement | O69: relationship
A70: Step 03 | B70: SEC-06 | C70: Requirement Trace | D70: 6.2 | E70: 2 | F70: Micro | G70: Trace result | H70: The outcome of the gate for this feature. | N70: feature | O70: (2 columns)
A71: Step 03 | B71: SEC-06 | C71: Requirement Trace | D71: 6.2.1 | E71: 3 | F71: Nano | G71: Trace status | H71: Traced when at least one Implemented by link exists, otherwise New insight. | I71: enum | J71: derived | K71: required | L71: list: TraceState | M71: Traced | N71: feature | O71: trace_status
A72: Step 03 | B72: SEC-06 | C72: Requirement Trace | D72: 6.2.2 | E72: 3 | F72: Nano | G72: New insight reason | H72: Why a requirement is missing for this feature. | I72: text | J72: atomic | K72: conditional | L72: required when status is New insight | M72: Competitor has it and we have no requirement | N72: feature | O72: new_insight_reason
A73: Step 03 | B73: SEC-06 | C73: Requirement Trace | D73: 6.3 | E73: 2 | F73: Micro | G73: Built where | H73: Where the feature lives in the database and how well it is tested. | N73: feature | O73: (6 columns)
A74: Step 03 | B74: SEC-06 | C74: Requirement Trace | D74: 6.3.1 | E74: 3 | F74: Nano | G74: Modules | H74: The database modules that implement it. | I74: text | J74: atomic | K74: optional | L74: comma separated names | M74: Profile | N74: feature | O74: modules
A75: Step 03 | B75: SEC-06 | C75: Requirement Trace | D75: 6.3.2 | E75: 3 | F75: Nano | G75: Tables used | H75: The tables that hold its data. | I75: text | J75: atomic | K75: optional | L75: comma separated table names | M75: candidate_profile | N75: feature | O75: tables_used
A76: Step 03 | B76: SEC-06 | C76: Requirement Trace | D76: 6.3.3 | E76: 3 | F76: Nano | G76: Key columns | H76: The main columns that carry it. | I76: text | J76: atomic | K76: optional | L76: comma separated table.column | M76: candidate_profile.headline | N76: feature | O76: key_columns
A77: Step 03 | B77: SEC-06 | C77: Requirement Trace | D77: 6.3.4 | E77: 3 | F77: Nano | G77: Decision ids | H77: The decisions in the decision log that explain the design. | I77: text | J77: atomic | K77: optional | L77: comma separated ids | M77: D6 | N77: feature | O77: decision_ids
A78: Step 03 | B78: SEC-06 | C78: Requirement Trace | D78: 6.3.5 | E78: 3 | F78: Nano | G78: Tests total | H78: How many generated test cases cover its tables. | I78: integer | J78: derived | K78: optional | L78: 0 or more | M78: 122 | N78: feature | O78: tests_total
A79: Step 03 | B79: SEC-06 | C79: Requirement Trace | D79: 6.3.6 | E79: 3 | F79: Nano | G79: Tests passed | H79: How many of those test cases passed. | I79: integer | J79: derived | K79: optional | L79: 0 to tests total | M79: 119 | N79: feature | O79: tests_passed
A80: Step 03 | B80: SEC-07 | C80: Competitor Gaps | D80: 7 | E80: 1 | F80: Macro | G80: Competitor Gaps | H80: What competitors lack, or what we lack, and why it matters. | N80: competitor_gap
A81: Step 03 | B81: SEC-07 | C81: Competitor Gaps | D81: 7.1 | E81: 2 | F81: Micro | G81: Gap | H81: Which gap it is and in which direction. | N81: competitor_gap | O81: (4 columns)
A82: Step 03 | B82: SEC-07 | C82: Competitor Gaps | D82: 7.1.1 | E82: 3 | F82: Nano | G82: Gap id | H82: One fixed code for the gap. | I82: id | J82: atomic | K82: required | L82: unique, pattern GAP-nn | M82: GAP-01 | N82: competitor_gap | O82: gap_id
A83: Step 03 | B83: SEC-07 | C83: Competitor Gaps | D83: 7.1.2 | E83: 3 | F83: Nano | G83: Feature id | H83: The feature the gap is about. | I83: reference | J83: atomic | K83: required | L83: an existing feature_id | M83: FD-052 | N83: competitor_gap | O83: feature_id
A84: Step 03 | B84: SEC-07 | C84: Competitor Gaps | D84: 7.1.3 | E84: 3 | F84: Nano | G84: Gap direction | H84: Competitors lack it, or we lack it. | I84: enum | J84: atomic | K84: required | L84: list: GapDirection | M84: Competitors lack it | N84: competitor_gap | O84: gap_direction
A85: Step 03 | B85: SEC-07 | C85: Competitor Gaps | D85: 7.1.4 | E85: 3 | F85: Nano | G85: Lack nature | H85: Absent, partial, not found on the pages checked, or not observable. | I85: enum | J85: atomic | K85: required | L85: list: LackNature | M85: Absent | N85: competitor_gap | O85: lack_nature
A86: Step 03 | B86: SEC-07 | C86: Competitor Gaps | D86: 7.2 | E86: 2 | F86: Micro | G86: Evidence | H86: What the claim rests on. | N86: competitor_gap | O86: (2 columns)
A87: Step 03 | B87: SEC-07 | C87: Competitor Gaps | D87: 7.2.1 | E87: 3 | F87: Nano | G87: Gap evidence | H87: The text or register row that shows the gap. | I87: text | J87: atomic | K87: required | L87: 1 to 500 characters | M87: Register says the products do not offer blocking by party type | N87: competitor_gap | O87: gap_evidence
A88: Step 03 | B88: SEC-07 | C88: Competitor Gaps | D88: 7.2.2 | E88: 3 | F88: Nano | G88: Evidence status | H88: Public if read on a live page, Known if from the register only. | I88: enum | J88: atomic | K88: required | L88: list: EvidenceStatus | M88: Known | N88: competitor_gap | O88: evidence_status
A89: Step 03 | B89: SEC-07 | C89: Competitor Gaps | D89: 7.3 | E89: 2 | F89: Micro | G89: Why it matters | H89: The argument. | N89: competitor_gap | O89: (4 columns)
A90: Step 03 | B90: SEC-07 | C90: Competitor Gaps | D90: 7.3.1 | E90: 3 | F90: Nano | G90: Reason type | H90: Why competitors lack it: technical, regulatory, commercial, not their focus or unknown. | I90: enum | J90: atomic | K90: required | L90: list: ReasonType | M90: Not their focus | N90: competitor_gap | O90: reason_type
A91: Step 03 | B91: SEC-07 | C91: Competitor Gaps | D91: 7.3.2 | E91: 3 | F91: Nano | G91: Why it matters | H91: The business reason in plain words. | I91: text | J91: atomic | K91: required | L91: 1 to 600 characters | M91: A candidate decides who may see them | N91: competitor_gap | O91: why_it_matters
A92: Step 03 | B92: SEC-07 | C92: Competitor Gaps | D92: 7.3.3 | E92: 3 | F92: Nano | G92: Persona affected | H92: The type of person who gains most. | I92: enum | J92: atomic | K92: required | L92: list: Persona | M92: Candidate | N92: competitor_gap | O92: persona_affected
A93: Step 03 | B93: SEC-07 | C93: Competitor Gaps | D93: 7.3.4 | E93: 3 | F93: Nano | G93: Impact dimension | H93: What improves: trust, cost, speed, match quality and so on. | I93: enum | J93: atomic | K93: required | L93: list: ImpactDimension | M93: Trust and safety | N93: competitor_gap | O93: impact_dimension
A94: Step 03 | B94: SEC-07 | C94: Competitor Gaps | D94: 7.4 | E94: 2 | F94: Micro | G94: Our answer | H94: What we did about it and how we prove it. | N94: competitor_gap | O94: (4 columns)
A95: Step 03 | B95: SEC-07 | C95: Competitor Gaps | D95: 7.4.1 | E95: 3 | F95: Nano | G95: What we built | H95: The tables and rules that answer the gap. | I95: text | J95: atomic | K95: required | L95: 1 to 500 characters | M95: Blocking lists in Administration | N95: competitor_gap | O95: what_we_built
A96: Step 03 | B96: SEC-07 | C96: Competitor Gaps | D96: 7.4.2 | E96: 3 | F96: Nano | G96: Proof type | H96: Automated test, decision record, competitor evidence or document. | I96: enum | J96: atomic | K96: required | L96: list: ProofType | M96: Automated test | N96: competitor_gap | O96: proof_type
A97: Step 03 | B97: SEC-07 | C97: Competitor Gaps | D97: 7.4.3 | E97: 3 | F97: Nano | G97: Proof reference | H97: The test file, decision id or page that proves it. | I97: text | J97: atomic | K97: required | L97: 1 to 300 characters | M97: tests/extra_security.sql | N97: competitor_gap | O97: proof_reference
A98: Step 03 | B98: SEC-07 | C98: Competitor Gaps | D98: 7.4.4 | E98: 3 | F98: Nano | G98: Action | H98: Build next, keep, verify first or skip. | I98: enum | J98: atomic | K98: required | L98: list: Action | M98: Keep | N98: competitor_gap | O98: action
A99: Step 03 | B99: SEC-08 | C99: Review Log | D99: 8 | E99: 1 | F99: Macro | G99: Review Log | H99: The review, review, review loop: every round is recorded. | N99: review_log
A100: Step 03 | B100: SEC-08 | C100: Review Log | D100: 8.1 | E100: 2 | F100: Micro | G100: Review record | H100: Which review it was. | N100: review_log | O100: (3 columns)
...

Sheet Schema register
A1: Table | B1: Column | C1: Data type | D1: Required | E1: Key | F1: Allowed values | G1: Used by id | H1: Sub-parameter | I1: Section ID | J1: L4 atomic definition
A2: study | B2: study_id | C2: id | D2: required | E2: Primary key | F2: unique, pattern FDS-nn | G2: 1.1.1 | H2: Study id | I2: SEC-01 | J2: Study id: one id value, required; rule: unique, pattern FDS-nn.
A3: study | B3: product_name | C3: text | D3: required | F3: 1 to 100 characters | G3: 1.1.2 | H3: Product name | I3: SEC-01 | J3: Product name: one text value, required; rule: 1 to 100 characters.
A4: study | B4: stage | C4: enum | D4: required | F4: list: Stage | G4: 1.1.3 | H4: Stage | I4: SEC-01 | J4: Stage: one enum value, required; rule: list: Stage.
A5: study | B5: method_type | C5: enum | D5: required | F5: list: MethodType | G5: 1.2.1 | H5: Method type | I5: SEC-01 | J5: Method type: one enum value, required; rule: list: MethodType.
A6: study | B6: schema_version | C6: text | D6: required | F6: pattern n.n | G6: 1.2.2 | H6: Schema version | I6: SEC-01 | J6: Schema version: one text value, required; rule: pattern n.n.
A7: study | B7: study_date | C7: date | D7: required | F7: date, not in the future | G7: 1.2.3 | H7: Study date | I7: SEC-01 | J7: Study date: one date value, required; rule: date, not in the future.
A8: competitor | B8: competitor_id | C8: id | D8: required | E8: Primary key | F8: unique, pattern COMP-nn | G8: 2.1.1 | H8: Competitor id | I8: SEC-02 | J8: Competitor id: one id value, required; rule: unique, pattern COMP-nn.
A9: competitor | B9: study_id | C9: reference | D9: required | E9: Foreign key to study.study_id | H9: Key column, not a parameter | I9: Key link | J9: Key link to the study.
A10: competitor | B10: competitor_name | C10: text | D10: required | F10: 1 to 100 characters | G10: 2.1.2 | H10: Competitor name | I10: SEC-02 | J10: Competitor name: one text value, required; rule: 1 to 100 characters.
A11: competitor | B11: product_type | C11: enum | D11: required | F11: list: ProductType | G11: 2.1.3 | H11: Product type | I11: SEC-02 | J11: Product type: one enum value, required; rule: list: ProductType.
A12: competitor | B12: tier | C12: enum | D12: required | F12: list: Tier | G12: 2.1.4 | H12: Tier | I12: SEC-02 | J12: Tier: one enum value, required; rule: list: Tier.
A13: competitor | B13: study_scope | C13: enum | D13: required | F13: list: StudyScope | G13: 2.2.1 | H13: Scope | I13: SEC-02 | J13: Scope: one enum value, required; rule: list: StudyScope.
A14: competitor | B14: pages_studied | C14: integer | D14: required | F14: 0 or more | G14: 2.2.2 | H14: Pages studied | I14: SEC-02 | J14: Pages studied: one integer value, required; rule: 0 or more.
A15: competitor | B15: access_level | C15: enum | D15: required | F15: list: PageAccess | G15: 2.2.3 | H15: Access level | I15: SEC-02 | J15: Access level: one enum value, required; rule: list: PageAccess.
A16: competitor | B16: last_checked_on | C16: date | D16: optional | F16: date, not in the future | G16: 2.3.1 | H16: Last checked on | I16: SEC-02 | J16: Last checked on: one date value, optional; rule: date, not in the future.
A17: competitor | B17: evidence_status | C17: enum | D17: required | F17: list: EvidenceStatus | G17: 2.3.2 | H17: Evidence status | I17: SEC-02 | J17: Evidence status: one enum value, required; rule: list: EvidenceStatus.
A18: feature | B18: feature_id | C18: id | D18: required | E18: Primary key | F18: unique, pattern FD-nnn | G18: 3.1.1 | H18: Feature id | I18: SEC-03 | J18: Feature id: one id value, required; rule: unique, pattern FD-nnn.
A19: feature | B19: study_id | C19: reference | D19: required | E19: Foreign key to study.study_id | H19: Key column, not a parameter | I19: Key link | J19: Key link to the study.
A20: feature | B20: feature_name | C20: text | D20: required | F20: 1 to 150 characters, unique | G20: 3.1.2 | H20: Feature name | I20: SEC-03 | J20: Feature name: one text value, required; rule: 1 to 150 characters, unique.
A21: feature | B21: feature_level | C21: enum | D21: required | F21: list: FeatureLevel | G21: 3.1.3 | H21: Feature level | I21: SEC-03 | J21: Feature level: one enum value, required; rule: list: FeatureLevel.
A22: feature | B22: parent_feature_id | C22: reference | D22: conditional | F22: an existing feature_id; required when level is Capability | G22: 3.1.4 | H22: Parent feature id | I22: SEC-03 | J22: Parent feature id: one reference value, conditional; rule: an existing feature_id; required when level is Capability.
A23: feature | B23: description | C23: text | D23: required | F23: 1 to 500 characters | G23: 3.2.1 | H23: Plain description | I23: SEC-03 | J23: Plain description: one text value, required; rule: 1 to 500 characters.
A24: feature | B24: category | C24: enum | D24: required | F24: list: Category | G24: 3.2.2 | H24: Category | I24: SEC-03 | J24: Category: one enum value, required; rule: list: Category.
A25: feature | B25: persona | C25: enum | D25: required | F25: list: Persona | G25: 3.2.3 | H25: Persona | I25: SEC-03 | J25: Persona: one enum value, required; rule: list: Persona.
A26: feature | B26: scope | C26: enum | D26: required | F26: list: ComparisonScope | G26: 3.2.4 | H26: Scope | I26: SEC-03 | J26: Scope: one enum value, required; rule: list: ComparisonScope.
A27: feature | B27: source_type | C27: enum | D27: required | F27: list: SourceType | G27: 3.3.1 | H27: Source type | I27: SEC-03 | J27: Source type: one enum value, required; rule: list: SourceType.
A28: feature | B28: source_reference | C28: text | D28: required | F28: 1 to 200 characters | G28: 3.3.2 | H28: Source reference | I28: SEC-03 | J28: Source reference: one text value, required; rule: 1 to 200 characters.
A29: feature | B29: scope_decision | C29: enum | D29: required | F29: list: ScopeDecision | G29: 3.4.1 | H29: Scope decision | I29: SEC-03 | J29: Scope decision: one enum value, required; rule: list: ScopeDecision.
A30: feature | B30: decision_reason | C30: text | D30: conditional | F30: required when the decision is not Keep | G30: 3.4.2 | H30: Decision reason | I30: SEC-03 | J30: Decision reason: one text value, conditional; rule: required when the decision is not Keep.
A31: feature | B31: classification | C31: enum | D31: required | F31: list: Class | G31: 4.1.1 | H31: Classification | I31: SEC-04 | J31: Classification: one enum value, required; rule: list: Class.
... A47: feature | B47: tests_passed | C47: integer | D47: optional | F47: 0 to tests total | G47: 6.3.6 | H47: Tests passed | I47: SEC-06 | J47: Derived: worked out from other columns.
A48: competitor_coverage | B48: feature_id | C48: reference | D48: required | E48: Primary key (part 1) and foreign key to feature.feature_id | F48: an existing feature_id | G48: 5.1.1 | H48: Feature id | I48: SEC-05 | J48: Feature id: one reference value, required; rule: an existing feature_id.
A49: competitor_coverage | B49: competitor_id | C49: reference | D49: required | E49: Primary key (part 2) and foreign key to competitor.competitor_id | F49: an existing competitor_id | G49: 5.1.2 | H49: Competitor id | I49: SEC-05 | J49: Competitor id: one reference value, required; rule: an existing competitor_id.
A50: competitor_coverage | B50: offering | C50: enum | D50: required | F50: list: CellValue | G50: 5.2.1 | H50: Offering | I50: SEC-05 | J50: Offering: one enum value, required; rule: list: CellValue.
A51: competitor_coverage | B51: offering_note | C51: text | D51: optional | F51: 0 to 300 characters | G51: 5.2.2 | H51: Offering note | I51: SEC-05 | J51: Offering note: one text value, optional; rule: 0 to 300 characters.
A52: competitor_coverage | B52: evidence_type | C52: enum | D52: required | F52: list: EvidenceType | G52: 5.3.1 | H52: Evidence type | I52: SEC-05 | J52: Evidence type: one enum value, required; rule: list: EvidenceType.
A53: competitor_coverage | B53: evidence_source | C53: text | D53: required | F53: 1 to 300 characters | G53: 5.3.2 | H53: Evidence source | I53: SEC-05 | J53: Evidence source: one text value, required; rule: 1 to 300 characters.
A54: competitor_coverage | B54: checked_on | C54: date | D54: optional | F54: date, not in the future | G54: 5.3.3 | H54: Checked on | I54: SEC-05 | J54: Checked on: one date value, optional; rule: date, not in the future.
A55: feature_requirement | B55: feature_id | C55: reference | D55: required | E55: Primary key (part 1) and foreign key to feature.feature_id | F55: an existing feature_id | G55: 6.1.1 | H55: Feature id | I55: SEC-06 | J55: Feature id: one reference value, required; rule: an existing feature_id.
A56: feature_requirement | B56: requirement_id | C56: text | D56: required | E56: Primary key (part 2); points to the Requirements workbook, not to a table here | F56: pattern FR-xxx or NFR-nn | G56: 6.1.2 | H56: Requirement id | I56: SEC-06 | J56: Requirement id: one text value, required; rule: pattern FR-xxx or NFR-nn.
A57: feature_requirement | B57: relationship | C57: enum | D57: required | F57: list: Relationship | G57: 6.1.3 | H57: Relationship | I57: SEC-06 | J57: Relationship: one enum value, required; rule: list: Relationship.
A58: competitor_gap | B58: gap_id | C58: id | D58: required | E58: Primary key | F58: unique, pattern GAP-nn | G58: 7.1.1 | H58: Gap id | I58: SEC-07 | J58: Gap id: one id value, required; rule: unique, pattern GAP-nn.
A59: competitor_gap | B59: feature_id | C59: reference | D59: required | E59: Foreign key to feature.feature_id | F59: an existing feature_id | G59: 7.1.2 | H59: Feature id | I59: SEC-07 | J59: Feature id: one reference value, required; rule: an existing feature_id.
A60: competitor_gap | B60: gap_direction | C60: enum | D60: required | F60: list: GapDirection | G60: 7.1.3 | H60: Gap direction | I60: SEC-07 | J60: Gap direction: one enum value, required; rule: list: GapDirection.
A61: competitor_gap | B61: lack_nature | C61: enum | D61: required | F61: list: LackNature | G61: 7.1.4 | H61: Lack nature | I61: SEC-07 | J61: Lack nature: one enum value, required; rule: list: LackNature.
A62: competitor_gap | B62: gap_evidence | C62: text | D62: required | F62: 1 to 500 characters | G62: 7.2.1 | H62: Gap evidence | I62: SEC-07 | J62: Gap evidence: one text value, required; rule: 1 to 500 characters.
A63: competitor_gap | B63: evidence_status | C63: enum | D63: required | F63: list: EvidenceStatus | G63: 7.2.2 | H63: Evidence status | I63: SEC-07 | J63: Evidence status: one enum value, required; rule: list: EvidenceStatus.
A64: competitor_gap | B64: reason_type | C64: enum | D64: required | F64: list: ReasonType | G64: 7.3.1 | H64: Reason type | I64: SEC-07 | J64: Reason type: one enum value, required; rule: list: ReasonType.
A65: competitor_gap | B65: why_it_matters | C65: text | D65: required | F65: 1 to 600 characters | G65: 7.3.2 | H65: Why it matters | I65: SEC-07 | J65: Why it matters: one text value, required; rule: 1 to 600 characters.
A66: competitor_gap | B66: persona_affected | C66: enum | D66: required | F66: list: Persona | G66: 7.3.3 | H66: Persona affected | I66: SEC-07 | J66: Persona affected: one enum value, required; rule: list: Persona.
A67: competitor_gap | B67: impact_dimension | C67: enum | D67: required | F67: list: ImpactDimension | G67: 7.3.4 | H67: Impact dimension | I67: SEC-07 | J67: Impact dimension: one enum value, required; rule: list: ImpactDimension.
A68: competitor_gap | B68: what_we_built | C68: text | D68: required | F68: 1 to 500 characters | G68: 7.4.1 | H68: What we built | I68: SEC-07 | J68: What we built: one text value, required; rule: 1 to 500 characters.
A69: competitor_gap | B69: proof_type | C69: enum | D69: required | F69: list: ProofType | G69: 7.4.2 | H69: Proof type | I69: SEC-07 | J69: Proof type: one enum value, required; rule: list: ProofType.
A70: competitor_gap | B70: proof_reference | C70: text | D70: required | F70: 1 to 300 characters | G70: 7.4.3 | H70: Proof reference | I70: SEC-07 | J70: Proof reference: one text value, required; rule: 1 to 300 characters.
A71: competitor_gap | B71: action | C71: enum | D71: required | F71: list: Action | G71: 7.4.4 | H71: Action | I71: SEC-07 | J71: Action: one enum value, required; rule: list: Action.
A72: review_log | B72: review_id | C72: id | D72: required | E72: Primary key | F72: unique, pattern REV-nn | G72: 8.1.1 | H72: Review id | I72: SEC-08 | J72: Review id: one id value, required; rule: unique, pattern REV-nn.
A73: review_log | B73: study_id | C73: reference | D73: required | E73: Foreign key to study.study_id | H73: Key column, not a parameter | I73: Key link | J73: Key link to the study.
A74: review_log | B74: review_round | C74: integer | D74: required | F74: 1 or more | G74: 8.1.2 | H74: Review round | I74: SEC-08 | J74: Review round: one integer value, required; rule: 1 or more.
A75: review_log | B75: review_type | C75: enum | D75: required | F75: list: ReviewType | G75: 8.1.3 | H75: Review type | I75: SEC-08 | J75: Review type: one enum value, required; rule: list: ReviewType.
A76: review_log | B76: reviewer | C76: text | D76: required | F76: 1 to 100 characters | G76: 8.2.1 | H76: Reviewer | I76: SEC-08 | J76: Reviewer: one text value, required; rule: 1 to 100 characters.
A77: review_log | B77: outcome | C77: enum | D77: required | F77: list: ReviewOutcome | G77: 8.2.2 | H77: Outcome | I77: SEC-08 | J77: Outcome: one enum value, required; rule: list: ReviewOutcome.
A78: review_log | B78: change_summary | C78: text | D78: optional | F78: 0 to 500 characters | G78: 8.2.3 | H78: Change summary | I78: SEC-08 | J78: Change summary: one text value, optional; rule: 0 to 500 characters.
A79: review_log | B79: reviewed_on | C79: date | D79: required | F79: date, not in the future | G79: 8.2.4 | H79: Reviewed on | I79: SEC-08 | J79: Reviewed on: one date value, required; rule: date, not in the future.
A80: nfr | B80: nfr_id | C80: id | D80: required | E80: Primary key | F80: unique, pattern NFR-nn | G80: 9.1.1 | H80: NFR id | I80: SEC-09 | J80: NFR id: one id value, required; rule: unique, pattern NFR-nn.
A81: nfr | B81: category | C81: enum | D81: required | F81: list: NfrCategory | G81: 9.1.2 | H81: Quality area | I81: SEC-09 | J81: Quality area: one enum value, required; rule: list: NfrCategory.
A82: nfr | B82: requirement_statement | C82: text | D82: required | F82: 1 to 500 characters | G82: 9.1.3 | H82: Requirement statement | I82: SEC-09 | J82: Requirement statement: one text value, required; rule: 1 to 500 characters.
A83: nfr | B83: source_reference | C83: text | D83: required | F83: 1 to 200 characters | G83: 9.2.1 | H83: Source reference | I83: SEC-09 | J83: Source reference: one text value, required; rule: 1 to 200 characters.
A84: nfr | B84: metric | C84: text | D84: required | F84: 1 to 150 characters | G84: 10.1.1 | H84: Metric | I84: SEC-10 | J84: Metric: one text value, required; rule: 1 to 150 characters.
A85: nfr | B85: unit | C85: text | D85: conditional | F85: required when a target value is set | G85: 10.1.2 | H85: Unit | I85: SEC-10 | J85: Unit: one text value, conditional; rule: required when a target value is set.
A86: nfr | B86: comparator | C86: enum | D86: conditional | F86: list: Comparator; required when a target value is set | G86: 10.2.1 | H86: Comparator | I86: SEC-10 | J86: Comparator: one enum value, conditional; rule: list: Comparator; required when a target value is set.
A87: nfr | B87: target_value | C87: decimal | D87: conditional | F87: 0 or more | G87: 10.2.2 | H87: Target value | I87: SEC-10 | J87: Target value: one decimal value, conditional; rule: 0 or more.
A88: nfr | B88: target_text | C88: text | D88: required | F88: 1 to 300 characters | G88: 10.2.3 | H88: Target as written | I88: SEC-10 | J88: Target as written: one text value, required; rule: 1 to 300 characters.
A89: nfr | B89: target_status | C89: enum | D89: required | F89: list: TargetStatus | G89: 10.2.4 | H89: Target status | I89: SEC-10 | J89: Target status: one enum value, required; rule: list: TargetStatus.
A90: nfr | B90: test_method | C90: text | D90: required | F90: 1 to 400 characters | G90: 11.1.1 | H90: Test method | I90: SEC-11 | J90: Test method: one text value, required; rule: 1 to 400 characters.
A91: nfr | B91: measured_by | C91: enum | D91: required | F91: list: MeasuredBy | G91: 11.1.2 | H91: Measured by | I91: SEC-11 | J91: Measured by: one enum value, required; rule: list: MeasuredBy.
A92: nfr | B92: evidence_reference | C92: text | D92: optional | F92: 0 to 300 characters | G92: 11.1.3 | H92: Evidence reference | I92: SEC-11 | J92: Evidence reference: one text value, optional; rule: 0 to 300 characters.
... A97: nfr | B97: status_detail | C97: text | D97: optional | F97: 0 to 400 characters | G97: 13.1.2 | H97: Status detail | I97: SEC-13 | J97: Status detail: one text value, optional; rule: 0 to 400 characters.
A98: nfr | B98: study_id | C98: id | D98: required | E98: Foreign key | F98: an existing study_id | H98: Key link to the study | I98: Key link | J98: Key link to the study.
A99: requirement | B99: requirement_id | C99: id | D99: required | E99: Primary key | F99: unique, pattern FR-xnn | G99: 14.1.1 | H99: Requirement id | I99: SEC-14 | J99: Requirement id: one id value, required; rule: unique, pattern FR-xnn.
A100: requirement | B100: module | C100: text | D100: required | F100: 1 to 60 characters | G100: 14.1.2 | H100: Module | I100: SEC-14 | J100: Module: one text value, required; rule: 1 to 60 characters.
A101: requirement | B101: requirement_statement | C101: text | D101: required | F101: 1 to 500 characters | G101: 14.1.3 | H101: Requirement statement | I101: SEC-14 | J101: Requirement statement: one text value, required; rule: 1 to 500 characters.
A102: requirement | B102: source_type | C102: enum | D102: required | F102: list: ReqSource | G102: 15.1.1 | H102: Source type | I102: SEC-15 | J102: Source type: one enum value, required; rule: list: ReqSource.
A103: requirement | B103: source_reference | C103: text | D103: conditional | F103: required unless the source type is Not recorded | G103: 15.1.2 | H103: Source reference | I103: SEC-15 | J103: Source reference: one text value, conditional; rule: required unless the source type is Not recorded.
A104: requirement | B104: actor | C104: enum | D104: required | F104: list: Persona | G104: 15.2.1 | H104: Actor | I104: SEC-15 | J104: Actor: one enum value, required; rule: list: Persona.
A105: requirement | B105: priority | C105: enum | D105: required | F105: list: Class | G105: 16.1.1 | H105: Priority | I105: SEC-16 | J105: Priority: one enum value, required; rule: list: Class.
A106: requirement | B106: priority_basis | C106: enum | D106: required | F106: list: PriorityBasis | G106: 16.1.2 | H106: Priority basis | I106: SEC-16 | J106: Priority basis: one enum value, required; rule: list: PriorityBasis.
A107: requirement | B107: ambiguity_note | C107: text | D107: optional | F107: 0 to 400 characters | G107: 16.2.1 | H107: Ambiguity note | I107: SEC-16 | J107: Ambiguity note: one text value, optional; rule: 0 to 400 characters.
A108: requirement | B108: our_status | C108: enum | D108: required | F108: list: ReqStatus | G108: 17.1.1 | H108: Our status | I108: SEC-17 | J108: Our status: one enum value, required; rule: list: ReqStatus.
A109: requirement | B109: status_detail | C109: text | D109: optional | F109: 0 to 400 characters | G109: 17.1.2 | H109: Status detail | I109: SEC-17 | J109: Status detail: one text value, optional; rule: 0 to 400 characters.
A110: requirement | B110: evidence_reference | C110: text | D110: optional | F110: 0 to 500 characters | G110: 17.1.3 | H110: Evidence reference | I110: SEC-17 | J110: Evidence reference: one text value, optional; rule: 0 to 500 characters.
A111: requirement | B111: tables_used | C111: text | D111: optional | F111: comma separated table names | G111: 17.1.4 | H111: Tables used | I111: SEC-17 | J111: Tables used: one text value, optional; rule: comma separated table names.
A112: scope_line | B112: scope_id | C112: id | D112: required | E112: Primary key | F112: unique, pattern SC-nnn | G112: 18.1.1 | H112: Scope line id | I112: SEC-18 | J112: Scope line id: one id value, required; rule: unique, pattern SC-nnn.
A113: scope_line | B113: line_type | C113: enum | D113: required | F113: list: LineType | G113: 18.1.2 | H113: Line type | I113: SEC-18 | J113: Line type: one enum value, required; rule: list: LineType.
A114: scope_line | B114: statement | C114: text | D114: required | F114: 1 to 500 characters | G114: 18.1.3 | H114: Statement | I114: SEC-18 | J114: Statement: one text value, required; rule: 1 to 500 characters.
A115: scope_line | B115: maps_to_requirement | C115: reference | D115: optional | F115: an existing requirement_id | G115: 18.2.1 | H115: Maps to requirement | I115: SEC-18 | J115: Maps to requirement: one reference value, optional; rule: an existing requirement_id.
A116: scope_line | B116: scope_source | C116: text | D116: required | F116: 1 to 200 characters | G116: 18.2.2 | H116: Source reference | I116: SEC-18 | J116: Source reference: one text value, required; rule: 1 to 200 characters.
A117: requirement | B117: study_id | C117: id | D117: required | E117: Foreign key | F117: an existing study_id | H117: Key link to the study | I117: Key link | J117: Key link to the study.
A118: scope_line | B118: study_id | C118: id | D118: required | E118: Foreign key | F118: an existing study_id | H118: Key link to the study | I118: Key link | J118: Key link to the study.

Sheet Allowed values
A1: List | B1: Value | C1: Meaning | D1: Used by sub-parameter | E1: Section ID
A2: Stage | B2: 01 Requirement analysis | C2: Stage 01: the requirement analysis docket. | D2: 1.1.3 Stage | E2: SEC-01
A3: Stage | B3: 02 Stakeholder personas and roles | C3: Stage 02: who uses the product and what each role may do. | E3: SEC-01
A4: Stage | B4: 03 Feature discovery | C4: Stage 03: this schema. Find what the product must do and what market leaders already do. | E4: SEC-01
A5: Stage | B5: 04 Non-functional requirements | C5: Stage 04: scale, speed, security, privacy, recovery targets. | E5: SEC-01
A6: MethodType | B6: Human only | C6: Every parameter value was written by a person. | D6: 1.2.1 Method type | E6: SEC-01
A7: MethodType | B7: LLM assisted | C7: A language model proposed values and a person checked every one. | E7: SEC-01
A8: MethodType | B8: Multi-LLM consolidated | C8: Two or more models or designers worked alone and a person consolidated the better parts. | E8: SEC-01
A9: ProductType | B9: Job portal | C9: A site where employers post jobs and candidates search and apply. | D9: 2.1.3 Product type | E9: SEC-02
A10: ProductType | B10: Professional network | C10: A social network whose members also search for jobs and people. | E10: SEC-02
A11: ProductType | B11: Campus hiring platform | C11: A platform for colleges and fresher hiring. | E11: SEC-02
A12: ProductType | B12: Other | C12: Any other kind of product. Say which in the reason studied. | E12: SEC-02
A13: Tier | B13: Leader | C13: A studied market leader. It counts in the classification rule. | D13: 2.1.4 Tier | E13: SEC-02
A14: Tier | B14: Specialist | C14: A leader in one scope only (for example campus). It counts only for that scope. | E14: SEC-02
A15: Tier | B15: Reference | C15: Studied for ideas. It does not count in the classification rule. | E15: SEC-02
A16: StudyScope | B16: General | C16: Studied for general features. | D16: 2.2.1 Scope | E16: SEC-02
A17: StudyScope | B17: Campus | C17: Studied for campus features only. | E17: SEC-02
A18: PageAccess | B18: Read | C18: The page was opened and read. | D18: 2.2.3 Access level | E18: SEC-02
A19: PageAccess | B19: Search summary only | C19: Only a search-engine summary of the page could be read. | E19: SEC-02
A20: PageAccess | B20: Not readable | C20: The page refused download or could not be read. | E20: SEC-02
A21: EvidenceStatus | B21: Public | C21: Checked on a public page of the product. | D21: 2.3.2 Evidence status; 4.2.2 Evidence status; 7.2.2 Evidence status | E21: SEC-02
A22: EvidenceStatus | B22: Known | C22: General knowledge, not checked on the live product. | E22: SEC-02
A23: EvidenceStatus | B23: Mixed | C23: Some cells Public and some Known. | E23: SEC-02
A24: EvidenceStatus | B24: Own design | C24: No competitor claim; our own design. | E24: SEC-02
A25: EvidenceStatus | B25: Search summary only | C25: Only a search-result summary of the page was seen | E25: SEC-02
A26: EvidenceStatus | B26: Verification log | C26: Taken from the verification log; not marked per row | E26: SEC-02
A27: EvidenceStatus | B27: Gap table | C27: Taken from the gap table; not marked per row | E27: SEC-02
A28: FeatureLevel | B28: Feature | C28: Something a user can see or do. It is compared with competitors. | D28: 3.1.3 Feature level | E28: SEC-03
A29: FeatureLevel | B29: Capability | C29: One requirement inside a feature that has several. It inherits the feature's class, matrix cells and verdict. | E29: SEC-03
A30: Category | B30: Profile | C30: The candidate's data: identity, skills, history, documents, visibility. | D30: 3.2.2 Category | E30: SEC-03
A31: Category | B31: Search | C31: Finding candidates or jobs by filters or keywords. | E31: SEC-03
A32: Category | B32: Jobs | C32: Posting and managing job requirements. | E32: SEC-03
A33: Category | B33: Applications | C33: Applying, the pipeline of statuses, withdrawing. | E33: SEC-03
A34: Category | B34: Hiring workflow | C34: Shortlists, interviews, offers, joining. | E34: SEC-03
A35: Category | B35: Consultants and sourcing | C35: Consultant requests, submissions, outreach. | E35: SEC-03
A36: Category | B36: Campus | C36: Campus drives and fresher hiring. | E36: SEC-03
A37: Category | B37: Gig | C37: Short assignments, bids and fulfilment. | E37: SEC-03
A38: Category | B38: Licences, subscriptions and wallet | C38: Seats, devices, plans, credits, payments, downloads. | E38: SEC-03
A39: Category | B39: Notifications and community | C39: Messages, preferences, posts and moderation. | E39: SEC-03
A40: Category | B40: Analytics | C40: Reports and marts built from the live data. | E40: SEC-03
A41: Category | B41: Organisation and admin | C41: Organisations, memberships, roles, consent, blocking, credentials. | E41: SEC-03
A42: Category | B42: Privacy and security | C42: Access control, audit, erasure, sensitive data, retention. | E42: SEC-03
A43: Category | B43: Platform and scale | C43: Partitioning, performance, recovery, data quality, reproducibility. | E43: SEC-03
A44: Persona | B44: Candidate | C44: A person looking for a job. | D44: 3.2.3 Persona; 7.3.3 Persona affected | E44: SEC-03
A45: Persona | B45: Recruiter | C45: A person who hires for an employer. | E45: SEC-03
A46: Persona | B46: Hiring manager | C46: The manager who owns the vacancy. | E46: SEC-03
A47: Persona | B47: Organisation administrator | C47: The person who runs an employer's account. | E47: SEC-03
A48: Persona | B48: Consultant | C48: A freelance recruiter who sources candidates. | E48: SEC-03
A49: Persona | B49: Gig worker | C49: A person taking short paid tasks. | E49: SEC-03
A50: Persona | B50: Placement officer | C50: A college officer who runs campus hiring. | E50: SEC-03
A51: Persona | B51: Platform administrator | C51: A person who runs the platform itself. | E51: SEC-03
A52: Persona | B52: Platform operator | C52: The team that operates the service. | E52: SEC-03
A53: Persona | B53: Compliance and privacy officer | C53: The person who checks privacy and legal rules. | E53: SEC-03
A54: Persona | B54: Data analyst | C54: A person who reads reports and marts. | E54: SEC-03
A55: Persona | B55: Integration service | C55: A system that talks to the platform. | E55: SEC-03
A56: ComparisonScope | B56: General | C56: Compared with the general market leaders. | D56: 3.2.4 Scope | E56: SEC-03
A57: ComparisonScope | B57: Campus | C57: Compared with the campus product only. One leader is studied, so the class is always provisional. | E57: SEC-03
A58: ComparisonScope | B58: Not observable | C58: Competitors do not show it to users (for example internal design), so no comparison claim is made. | E58: SEC-03
A59: SourceType | B59: Competitor register | C59: A row of the competitor coverage register. | D59: 3.3.1 Source type | E59: SEC-03
A60: SourceType | B60: Gap table | C60: A row of the register's gap table (a competitor has it, we may not). | E60: SEC-03
A61: SourceType | B61: Verification log | C61: A line of a verification log for one competitor. | E61: SEC-03
A62: SourceType | B62: Functional requirement | C62: A functional requirement of the requirements docket. | E62: SEC-03
A63: SourceType | B63: Domain primer | C63: A business idea described in the domain primer. | E63: SEC-03
A64: SourceType | B64: Own insight | C64: An idea of the team that no source row states. It must say why it matters. | E64: SEC-03
A65: ScopeDecision | B65: Keep | C65: The feature stays in Talentra's scope. | D65: 3.4.1 Scope decision | E65: SEC-03
A66: ScopeDecision | B66: Defer | C66: Wanted, but not in this round. A reason and a revisit point are stated. | E66: SEC-03
A67: ScopeDecision | B67: Drop | C67: Will not be built. The reason is stated and the feature stays in the inventory as a record. | E67: SEC-03
A68: Class | B68: MUST-HAVE | C68: Every studied leader offers it (Yes or Partial). For features the leaders do not show: the brief or a recorded rule demands it, with a citation. | D68: 4.1.1 Classification | E68: SEC-04
A69: Class | B69: SHOULD-HAVE | C69: At least one leader offers it or could (some cells Not verified) but not all are known to. Supporting capabilities not compared with competitors are also SHOULD-HAVE. | E69: SEC-04
A70: Class | B70: DIFFERENTIATOR | C70: At most one leader offers it, even if every Not verified cell turned out to be Yes (offering plus not verified is 1 or less). For campus: no leader offers it. | E70: SEC-04
A71: ClassBasis | B71: Competitor matrix rule | C71: The class follows from the matrix by the class rules. | D71: 4.1.2 Class basis | E71: SEC-04
A72: ClassBasis | B72: Brief demands | C72: A cited decision or document in the repository says the brief demands it. | E72: SEC-04
A73: ClassBasis | B73: Recorded rule | C73: A cited non-functional requirement or team decision demands it. | E73: SEC-04
A74: ClassBasis | B74: Supporting capability | C74: Not compared with competitors. Classed SHOULD-HAVE by declaration. | E74: SEC-04
A75: ClassBasis | B75: Declared market-wide | C75: Declared a differentiator because the market-wide feature is not shown by the studied leaders; the reason says why. | E75: SEC-04
A76: ClassBasis | B76: Inherited from parent feature | C76: A capability takes the class of its parent feature | E76: SEC-04
A77: ClassBasis | B77: Domain primer | C77: A hiring line the platform serves; not compared with competitors | E77: SEC-04
A78: Confidence | B78: Firm | C78: Every studied cell for the feature is verified. The class will not change. | D78: 4.2.1 Confidence | E78: SEC-04
A79: Confidence | B79: Provisional | C79: At least one cell is Not verified. The class may change when a person checks the live site. | E79: SEC-04
A80: Confidence | B80: Declared | C80: Not observable in competitors. The class is declared with a stated basis, not computed. | E80: SEC-04
A81: CellValue | B81: Yes | C81: The evidence says the product offers it. Counts as offering. | D81: 5.2.1 Offering | E81: SEC-05
A82: CellValue | B82: Partial | C82: Offered in a reduced or different form. Counts as offering. | E82: SEC-05
A83: CellValue | B83: No | C83: The evidence says it is absent, or it was not found on the pages checked (weaker proof). Does not count. | E83: SEC-05
A84: CellValue | B84: Not verified | C84: The evidence is general knowledge and nobody has checked the live product. Does not count as offering and may change the class. | E84: SEC-05
A85: EvidenceType | B85: Page read | C85: A page of the product that was opened and read. | D85: 5.3.1 Evidence type | E85: SEC-05
A86: EvidenceType | B86: Search summary | C86: A search-engine summary of an official page. | E86: SEC-05
A87: EvidenceType | B87: Register text | C87: Text of the competitor register row (may rest on general knowledge). | E87: SEC-05
A88: EvidenceType | B88: Repository document | C88: A document or decision in our repository. | E88: SEC-05
A89: EvidenceType | B89: Own design | C89: Our design; no competitor evidence. | E89: SEC-05
A90: OurCoverage | B90: Built and tested | C90: All its requirements are built and a test refuses a breach. | D90: 5.4.1 Our coverage | E90: SEC-05
A91: OurCoverage | B91: Built | C91: Built without a dedicated test. | E91: SEC-05
A92: OurCoverage | B92: Planned | C92: Designed for a later phase. | E92: SEC-05
A93: OurCoverage | B93: Not built | C93: No requirement yet. Usually a new insight. | E93: SEC-05
A94: OurCoverage | B94: Deliberately left out | C94: A recorded decision says it will not be built. | E94: SEC-05
A95: Verdict | B95: Matches | C95: We offer what the leaders offer. | D95: 5.4.2 Verdict | E95: SEC-05
A96: Verdict | B96: Exceeds | C96: We offer more, or better, than the studied leaders. | E96: SEC-05
A97: Verdict | B97: Falls short | C97: The leaders offer something we do not. | E97: SEC-05
A98: Verdict | B98: Planned | C98: We lack it today and have it planned. | E98: SEC-05
A99: Verdict | B99: Not compared | C99: The studied products do not show it, so no claim is made. | E99: SEC-05
A100: Relationship | B100: Implemented by | C100: The requirement, when built, delivers the feature. | D100: 6.1.3 Relationship | E100: SEC-06
...

Sheet Feature discovery
A1: Output document (draft, deliverable c): the 176 features and capabilities in the original column layout. Five columns were normalised to the schema's allowed values; the wording as first recorded is kept in the last column.
A3: ID | B3: Level | C3: Parent | D3: Feature | E3: Plain description | F3: Category | G3: Persona | H3: Source type | I3: Source reference | J3: Scope | K3: Classification | L3: Class basis | M3: Reason | N3: Confidence | O3: Evidence status | P3: Our coverage | Q3: Verdict | R3: Verdict source | S3: Trace status | T3: Note | U3: Rule check | V3: Recorded wording before normalising
A4: FD-001 | B4: Feature | D4: Resume headline and profile summary | E4: A short headline and a summary of the candidate, with the language of the text. | F4: Profile | G4: Candidate | H4: Competitor register | I4: Section 1: Candidate profile (row 1) | J4: General | K4: MUST-HAVE | L4: Competitor matrix rule | M4: 3 of 3 studied leaders offer it (Naukri, Monster, LinkedIn); 0 not verified. | N4: Firm | O4: Public | P4: Built and tested | Q4: Matches | R4: Register | S4: Traced | U4: OK | V4: Trace status: Traced to requirement
A5: FD-002 | B5: Feature | D5: Employment history with designation, organisation, duration, description | E5: Jobs held, with designation, organisation, dates and description, and the notice period. | F5: Profile | G5: Candidate | H5: Competitor register | I5: Section 1: Candidate profile (row 2) | J5: General | K5: MUST-HAVE | L5: Competitor matrix rule | M5: 3 of 3 studied leaders offer it (Naukri, Monster, LinkedIn); 0 not verified. | N5: Firm | O5: Public | P5: Built and tested | Q5: Matches | R5: Register | S5: Traced | U5: OK | V5: Trace status: Traced to requirement
A6: FD-003 | B6: Feature | D6: Education | E6: Qualifications with institution, grade and the grading scale used. | F6: Profile | G6: Candidate | H6: Competitor register | I6: Section 1: Candidate profile (row 3) | J6: General | K6: MUST-HAVE | L6: Competitor matrix rule | M6: 3 of 3 studied leaders offer it (Naukri, Monster, LinkedIn); 0 not verified. | N6: Firm | O6: Public | P6: Built and tested | Q6: Matches | R6: Register | S6: Traced | U6: OK | V6: Trace status: Traced to requirement
A7: FD-004 | B7: Feature | D7: Key skills | E7: Skills with level, years of use, last year used and where the skill came from. | F7: Profile | G7: Candidate | H7: Competitor register | I7: Section 1: Candidate profile (row 4) | J7: General | K7: MUST-HAVE | L7: Competitor matrix rule | M7: 3 of 3 studied leaders offer it (Naukri, Monster, LinkedIn); 0 not verified. | N7: Firm | O7: Public | P7: Built and tested | Q7: Exceeds | R7: Register | S7: Traced | U7: OK | V7: Trace status: Traced to requirement
A8: FD-005 | B8: Feature | D8: IT skills with software version | E8: A skill can carry the software version, so a search can tell one version of a tool from another. | F8: Profile | G8: Candidate | H8: Competitor register | I8: Section 1: Candidate profile (row 5) | J8: General | K8: DIFFERENTIATOR | L8: Competitor matrix rule | M8: 1 of 3 studied leaders offer it (Naukri); 0 not verified. | N8: Firm | O8: Known | P8: Built and tested | Q8: Matches | R8: Register | S8: Traced | U8: OK | V8: Trace status: Traced to requirement
A9: FD-006 | B9: Feature | D9: Languages | E9: Languages with separate read, write and speak levels. | F9: Profile | G9: Candidate | H9: Competitor register | I9: Section 1: Candidate profile (row 6) | J9: General | K9: SHOULD-HAVE | L9: Competitor matrix rule | M9: 1 of 3 studied leaders offer it (LinkedIn); 1 not verified. | N9: Provisional | O9: Public | P9: Built and tested | Q9: Exceeds | R9: Register | S9: Traced | U9: OK | V9: Trace status: Traced to requirement
A10: FD-007 | B10: Feature | D10: Certifications and licences | E10: Certificates and licences with a credential reference and an expiry date. | F10: Profile | G10: Candidate | H10: Competitor register | I10: Section 1: Candidate profile (row 7) | J10: General | K10: MUST-HAVE | L10: Competitor matrix rule | M10: 3 of 3 studied leaders offer it (Naukri, Monster, LinkedIn); 0 not verified. | N10: Firm | O10: Public | P10: Built and tested | Q10: Matches | R10: Register | S10: Traced | U10: OK | V10: Trace status: Traced to requirement
A11: FD-008 | B11: Feature | D11: Projects | E11: Projects done on a job or as gig work, with the skills used. | F11: Profile | G11: Candidate | H11: Competitor register | I11: Section 1: Candidate profile (row 8) | J11: General | K11: SHOULD-HAVE | L11: Competitor matrix rule | M11: 2 of 3 studied leaders offer it (Naukri, LinkedIn); 0 not verified. | N11: Firm | O11: Public | P11: Built and tested | Q11: Matches | R11: Register | S11: Traced | U11: OK | V11: Trace status: Traced to requirement
A12: FD-009 | B12: Feature | D12: Accomplishments: publications, patents, work samples | E12: Publications, patents, honours and work samples, kept as typed accomplishments. | F12: Profile | G12: Candidate | H12: Competitor register | I12: Section 1: Candidate profile (row 9) | J12: General | K12: SHOULD-HAVE | L12: Competitor matrix rule | M12: 2 of 3 studied leaders offer it (Naukri, LinkedIn); 0 not verified. | N12: Firm | O12: Public | P12: Built and tested | Q12: Matches | R12: Register | S12: Traced | U12: OK | V12: Trace status: Traced to requirement
A13: FD-010 | B13: Feature | D13: Volunteering and organisations | E13: Volunteer work and organisations the candidate belongs to. | F13: Profile | G13: Candidate | H13: Competitor register | I13: Section 1: Candidate profile (row 10) | J13: General | K13: DIFFERENTIATOR | L13: Competitor matrix rule | M13: 1 of 3 studied leaders offer it (LinkedIn); 0 not verified. | N13: Firm | O13: Public | P13: Built and tested | Q13: Matches | R13: Register | S13: Traced | U13: OK | V13: Trace status: Traced to requirement
A14: FD-011 | B14: Feature | D14: Recommendations and endorsements | E14: Other people recommend or endorse a candidate on the profile. | F14: Profile | G14: Candidate | H14: Competitor register | I14: Section 1: Candidate profile (row 11) | J14: General | K14: DIFFERENTIATOR | L14: Competitor matrix rule | M14: 1 of 3 studied leaders offer it (LinkedIn); 0 not verified. | N14: Firm | O14: Public | P14: Not built | Q14: Falls short | R14: Register | S14: New insight | U14: OK | V14: Trace status: NEW INSIGHT
A15: FD-012 | B15: Feature | D15: Courses | E15: Courses taken, with progress, as part of the profile. | F15: Profile | G15: Candidate | H15: Competitor register | I15: Section 1: Candidate profile (row 12) | J15: General | K15: SHOULD-HAVE | L15: Competitor matrix rule | M15: 1 of 3 studied leaders offer it (LinkedIn); 1 not verified. | N15: Provisional | O15: Public | P15: Built | Q15: Exceeds | R15: Register | S15: Traced | U15: OK | V15: Trace status: Traced to requirement
... A53: FD-050 | B53: Feature | D53: Gig marketplace with windows, pricing, one-way bids, external fulfilment (LinkedIn has a Services marketplace, with no windows or bids) | E53: Short tasks with a time window, a price, one-way bids and an outside fulfilment system. | F53: Gig | G53: Gig worker | H53: Competitor register | I53: Section 6: Things in Talentra that these products do not show to users (row 50) | J53: Not observable | K53: DIFFERENTIATOR | L53: Declared market-wide | M53: Register section 6: LinkedIn has a Services marketplace with no windows or bids; no other studied product shows one (evidence Known) | N53: Declared | O53: Known | P53: Built | Q53: Exceeds | R53: Register | S53: Traced | U53: declared | V53: Class basis: Register section 6: LinkedIn has a Services marketplace with no windows or bids; no other studied product shows one (evidence Known) | Confidence: Declared (not observable) | Trace status: Traced to requirement
A54: FD-051 | B54: Feature | D54: Consultant marketplace: freelance recruiters source for jobs open to consultants | E54: A consultant works only the jobs open to consultants, through a request the employer approves, with fee terms. | F54: Consultants and sourcing | G54: Consultant | H54: Competitor register | I54: Section 6: Things in Talentra that these products do not show to users (row 51) | J54: Not observable | K54: MUST-HAVE | L54: Brief demands | M54: Brief demands: a consultant acts only on requirements open to consultants (decision SO1) | N54: Declared | O54: Known | P54: Built and tested | Q54: Exceeds | R54: Register | S54: Traced | T54: Register verdict: Exceeds on the rule that a consultant acts only on open requirements; falls short on settlement and protection | U54: declared | V54: Class basis: Brief demands: a consultant acts only on requirements open to consultants (decision SO1) | Confidence: Declared (not observable) | Trace status: Traced to requirement
A55: FD-052 | B55: Feature | D55: Candidate can block employers, recruiters and consultants by party type (LinkedIn blocks any member) | E55: A candidate blocks an organisation or a person, and the blocked side cannot see the candidate. | F55: Privacy and security | G55: Candidate | H55: Competitor register | I55: Section 6: Things in Talentra that these products do not show to users (row 52) | J55: Not observable | K55: MUST-HAVE | L55: Brief demands | M55: Brief demands: the blocked-party rule (decision A7) | N55: Declared | O55: Known | P55: Built and tested | Q55: Exceeds | R55: Register | S55: Traced | U55: declared | V55: Class basis: Brief demands: the blocked-party rule (decision A7) | Confidence: Declared (not observable) | Trace status: Traced to requirement
A56: FD-053 | B56: Feature | D56: Rules enforced in the database (one application per job, no overlapping windows) | E56: One application per job and no overlapping windows, enforced by the database and not by the application. | F56: Platform and scale | G56: Platform operator | H56: Competitor register | I56: Section 6: Things in Talentra that these products do not show to users (row 53) | J56: Not observable | K56: MUST-HAVE | L56: Brief demands | M56: Brief demands: rules enforced by the database (docs/schema-justification.md) | N56: Declared | O56: Known | P56: Built and tested | Q56: Exceeds | R56: Register | S56: Traced | U56: declared | V56: Class basis: Brief demands: rules enforced by the database (docs/schema-justification.md) | Confidence: Declared (not observable) | Trace status: Traced to requirement
A57: FD-054 | B57: Feature | D57: Current and expected salary as fields and recruiter filters | E57: Current and expected pay stored on the candidate and usable as a recruiter filter. The columns exist on the profile; the search filter is not modelled. | F57: Search | G57: Recruiter | H57: Gap table | I57: Gap table, row 'Current and expected salary' | J57: General | K57: MUST-HAVE | L57: Competitor matrix rule | M57: 3 of 3 studied leaders offer it (Naukri, Monster, LinkedIn); 0 not verified. | N57: Firm | O57: Mixed | P57: Built | Q57: Falls short | R57: Our reading of the gap table | S57: Traced | T57: candidate_profile has expected_salary_min, expected_salary_max, currency and period; the register still lists this as Proposed. Filter on it is not built. | U57: OK | V57: Evidence status: Mixed: pages read and search summary | Trace status: Traced to requirement
A58: FD-055 | B58: Feature | D58: Serving notice flag | E58: A yes/no flag that the candidate is serving a notice period, kept apart from the length of the notice. | F58: Profile | G58: Candidate | H58: Gap table | I58: Gap table, row 'Serving notice flag' | J58: General | K58: SHOULD-HAVE | L58: Competitor matrix rule | M58: 1 of 3 studied leaders offer it (Naukri); 2 not verified. | N58: Provisional | O58: Search summary only | P58: Not built | Q58: Falls short | R58: Derived from the gap table | S58: New insight | T58: notice_period_days exists; the flag does not. | U58: OK | V58: Trace status: NEW INSIGHT
A59: FD-056 | B59: Feature | D59: Per-seat usage quota | E59: A weekly or monthly limit on what one user of a licence may view or send. | F59: Licences, subscriptions and wallet | G59: Organisation administrator | H59: Gap table | I59: Gap table, row 'Per-seat quota' | J59: General | K59: SHOULD-HAVE | L59: Competitor matrix rule | M59: 2 of 3 studied leaders offer it (Naukri, LinkedIn); 1 not verified. | N59: Provisional | O59: Mixed | P59: Not built | Q59: Falls short | R59: Derived from the gap table | S59: New insight | U59: OK | V59: Evidence status: Mixed: page read and search summary | Trace status: NEW INSIGHT
A60: FD-057 | B60: Feature | D60: Seat park, restore and reassign | E60: A seat can be parked, restored or handed to another user, with a monthly cap. | F60: Licences, subscriptions and wallet | G60: Organisation administrator | H60: Gap table | I60: Gap table, row 'Seat lifecycle' | J60: General | K60: SHOULD-HAVE | L60: Competitor matrix rule | M60: 1 of 3 studied leaders offer it (LinkedIn); 2 not verified. | N60: Provisional | O60: Search summary only | P60: Not built | Q60: Falls short | R60: Derived from the gap table | S60: New insight | T60: LinkedIn evidence is a search summary. | U60: OK | V60: Trace status: NEW INSIGHT
A61: FD-058 | B61: Feature | D61: Custom fields on a prospect | E61: Administrators define extra fields on a prospect and filter by them inside a pipeline. | F61: Consultants and sourcing | G61: Recruiter | H61: Gap table | I61: Gap table, row 'Admin-defined custom fields' | J61: General | K61: SHOULD-HAVE | L61: Competitor matrix rule | M61: 1 of 3 studied leaders offer it (LinkedIn); 2 not verified. | N61: Provisional | O61: Search summary only | P61: Deliberately left out | Q61: Falls short | R61: Derived from the gap table | S61: New insight | T61: Decision SO10: needs a generic field model that no other module uses, and the brief does not ask for it. | U61: OK | V61: Trace status: NEW INSIGHT
A62: FD-059 | B62: Feature | D62: Resume visible only through a campaign message | E62: A third resume privacy level: hidden from search but reachable by a campaign message. | F62: Profile | G62: Candidate | H62: Gap table | I62: Gap table, row 'Resume visibility private but reachable' | J62: General | K62: SHOULD-HAVE | L62: Competitor matrix rule | M62: 1 of 3 studied leaders offer it (Monster); 2 not verified. | N62: Provisional | O62: Public | P62: Not built | Q62: Falls short | R62: Derived from the gap table | S62: New insight | U62: OK | V62: Evidence status: Public: page read | Trace status: NEW INSIGHT
A63: FD-060 | B63: Feature | D63: Screening question library and auto-reject | E63: A catalogue of question types, a saved questionnaire library and an automatic rejection email. | F63: Applications | G63: Hiring manager | H63: Gap table | I63: Gap table, row 'Screening question type catalogue' | J63: General | K63: MUST-HAVE | L63: Competitor matrix rule | M63: 3 of 3 studied leaders offer it (Naukri, Monster, LinkedIn); 0 not verified. | N63: Firm | O63: Mixed | P63: Not built | Q63: Falls short | R63: Derived from the gap table | S63: New insight | U63: OK | V63: Evidence status: Mixed: page read and search summary | Trace status: NEW INSIGHT
A64: FD-061 | B64: Feature | D64: Filters on veteran status, clearance and graduation year | E64: Candidate attributes used as recruiter filters: military veteran, security clearance, year of graduation, resume updated window. | F64: Search | G64: Recruiter | H64: Gap table | I64: Gap table, row 'Candidate attributes used as employer filters' | J64: General | K64: SHOULD-HAVE | L64: Competitor matrix rule | M64: 2 of 3 studied leaders offer it (Monster, LinkedIn); 1 not verified. | N64: Provisional | O64: Public | P64: Not built | Q64: Falls short | R64: Derived from the gap table | S64: New insight | U64: OK | V64: Evidence status: Public: page read | Trace status: NEW INSIGHT
A65: FD-062 | B65: Feature | D65: Platform-issued skill certificates | E65: The platform tests a skill and issues a certificate the candidate can show. | F65: Profile | G65: Candidate | H65: Gap table | I65: Gap table, row 'Platform-issued skill certifications' | J65: General | K65: SHOULD-HAVE | L65: Competitor matrix rule | M65: 1 of 3 studied leaders offer it (Naukri); 2 not verified. | N65: Provisional | O65: Search summary only | P65: Not built | Q65: Falls short | R65: Derived from the gap table | S65: New insight | T65: Naukri evidence is a search summary. | U65: OK | V65: Trace status: NEW INSIGHT
A66: FD-063 | B66: Feature | D66: Alert and saved-job limits | E66: Caps on the number of job alerts and saved jobs a person may hold. | F66: Notifications and community | G66: Candidate | H66: Gap table | I66: Gap table, row 'Job alert and saved-job caps' | J66: General | K66: SHOULD-HAVE | L66: Competitor matrix rule | M66: 2 of 3 studied leaders offer it (Monster, LinkedIn); 1 not verified. | N66: Provisional | O66: Search summary only | P66: Not built | Q66: Falls short | R66: Derived from the gap table | S66: New insight | T66: The delivery side has a daily cap per person and channel (NT6); the alert definition and its limit are not built. | U66: OK | V66: Trace status: NEW INSIGHT
A67: FD-064 | B67: Feature | D67: Credit holding cap per plan | E67: Unused credits accumulate up to a cap set by the plan. | F67: Licences, subscriptions and wallet | G67: Organisation administrator | H67: Gap table | I67: Gap table, row 'InMail style refund and accumulation rules' | J67: General | K67: SHOULD-HAVE | L67: Competitor matrix rule | M67: 1 of 3 studied leaders offer it (LinkedIn); 2 not verified. | N67: Provisional | O67: Public | P67: Not built | Q67: Falls short | R67: Derived from the gap table | S67: New insight | T67: A reversal entry returns credits; the cap is not modelled. | U67: OK | V67: Evidence status: Public: page read | Trace status: NEW INSIGHT
A68: FD-065 | B68: Feature | D68: Outreach limit per candidate | E68: The same sender cannot contact the same candidate on the same channel more than once in 168 hours; the limit holds per person and per organisation. | F68: Consultants and sourcing | G68: Recruiter | H68: Gap table | I68: Gap table, row 'Outreach throttling per jobseeker' | J68: General | K68: SHOULD-HAVE | L68: Competitor matrix rule | M68: 2 of 3 studied leaders offer it (Naukri, LinkedIn); 1 not verified. | N68: Provisional | O68: Search summary only | P68: Built and tested | Q68: Matches | R68: Derived from the gap table | S68: Traced | T68: The limit of two different emails per week and the lock until reply are not built. | U68: OK | V68: Trace status: Traced to requirement
A69: FD-066 | B69: Feature | D69: Notification preferences and delivery controls | E69: A person sets preferences by topic and channel, quiet hours and a daily cap; unsubscribe and bounce handling; a mandatory topic for security alerts. | F69: Notifications and community | G69: Candidate | H69: Gap table | I69: Gap table, row 'Notification preferences' | J69: General | K69: MUST-HAVE | L69: Competitor matrix rule | M69: 3 of 3 studied leaders offer it (Naukri, Monster, LinkedIn); 0 not verified. | N69: Firm | O69: Gap table | P69: Built and tested | Q69: Matches | R69: Derived from the gap table | S69: Traced | U69: OK | V69: Evidence status: Gap table (evidence not marked per row) | Trace status: Traced to requirement
A70: FD-067 | B70: Feature | D70: Community posts and moderation | E70: Posts, comments, reactions and reports, with a moderation status, audited moderation and the blocking list respected. | F70: Notifications and community | G70: Candidate | H70: Gap table | I70: Gap table, row 'Community posts' | J70: General | K70: SHOULD-HAVE | L70: Competitor matrix rule | M70: 2 of 3 studied leaders offer it (Naukri, LinkedIn); 1 not verified. | N70: Provisional | O70: Gap table | P70: Built and tested | Q70: Matches | R70: Derived from the gap table | S70: Traced | U70: OK | V70: Evidence status: Gap table (evidence not marked per row) | Trace status: Traced to requirement
A71: FD-068 | B71: Feature | D71: Recruiter dashboards | E71: Applications by stage, credit use and delivery results, from daily marts that hide groups smaller than five. | F71: Analytics | G71: Data analyst | H71: Gap table | I71: Gap table, row 'Dashboards' | J71: General | K71: SHOULD-HAVE | L71: Competitor matrix rule | M71: 2 of 3 studied leaders offer it (Naukri, LinkedIn); 1 not verified. | N71: Provisional | O71: Gap table | P71: Built and tested | Q71: Matches | R71: Derived from the gap table | S71: Traced | U71: OK | V71: Evidence status: Gap table (evidence not marked per row) | Trace status: Traced to requirement
A72: FD-069 | B72: Feature | D72: Background photo and photo visibility | E72: A second picture and a setting for who may see the photo. | F72: Profile | G72: Candidate | H72: Verification log | I72: LinkedIn verification table | J72: General | K72: SHOULD-HAVE | L72: Competitor matrix rule | M72: 1 of 3 studied leaders offer it (LinkedIn); 2 not verified. | N72: Provisional | O72: Verification log | P72: Not built | Q72: Falls short | R72: Derived from the gap table | S72: New insight | U72: OK | V72: Source type: LinkedIn verification table | Evidence status: Verification log (page or snippet, not marked per row) | Trace status: NEW INSIGHT
A73: FD-070 | B73: Feature | D73: Open to work audience | E73: Who sees the open-to-work signal: all members, recruiters only, or only the person. | F73: Profile | G73: Candidate | H73: Verification log | I73: LinkedIn verification table | J73: General | K73: SHOULD-HAVE | L73: Competitor matrix rule | M73: 1 of 3 studied leaders offer it (LinkedIn); 2 not verified. | N73: Provisional | O73: Verification log | P73: Not built | Q73: Falls short | R73: Derived from the gap table | S73: New insight | U73: OK | V73: Source type: LinkedIn verification table | Evidence status: Verification log (page or snippet, not marked per row) | Trace status: NEW INSIGHT
A74: FD-071 | B74: Feature | D74: Kind of verification | E74: A verification badge by kind: identity, workplace or education. | F74: Profile | G74: Candidate | H74: Verification log | I74: LinkedIn verification table | J74: General | K74: SHOULD-HAVE | L74: Competitor matrix rule | M74: 1 of 3 studied leaders offer it (LinkedIn); 1 not verified. | N74: Provisional | O74: Verification log | P74: Not built | Q74: Falls short | R74: Derived from the gap table | S74: New insight | U74: OK | V74: Source type: LinkedIn verification table | Evidence status: Verification log (page or snippet, not marked per row) | Trace status: NEW INSIGHT
A75: FD-072 | B75: Feature | D75: Viewer visibility mode on a profile view | E75: A person can view a profile in a named visibility mode, and the view records it. | F75: Profile | G75: Candidate | H75: Verification log | I75: LinkedIn verification table | J75: General | K75: SHOULD-HAVE | L75: Competitor matrix rule | M75: 1 of 3 studied leaders offer it (LinkedIn); 2 not verified. | N75: Provisional | O75: Verification log | P75: Not built | Q75: Falls short | R75: Derived from the gap table | S75: New insight | U75: OK | V75: Source type: LinkedIn verification table | Evidence status: Verification log (page or snippet, not marked per row) | Trace status: NEW INSIGHT
A76: FD-073 | B76: Feature | D76: Richer job posting fields | E76: Seniority, job function, workplace type, pay frequency, benefits and the way to apply. | F76: Jobs | G76: Hiring manager | H76: Verification log | I76: LinkedIn verification table | J76: General | K76: SHOULD-HAVE | L76: Competitor matrix rule | M76: 1 of 3 studied leaders offer it (LinkedIn); 2 not verified. | N76: Provisional | O76: Verification log | P76: Not built | Q76: Falls short | R76: Derived from the gap table | S76: New insight | T76: Some, such as work mode, exist; the register lists seniority, function, benefits and apply method as missing. | U76: OK | V76: Source type: LinkedIn verification table | Evidence status: Verification log (page or snippet, not marked per row) | Trace status: NEW INSIGHT
A77: FD-074 | B77: Feature | D77: Must-have flag on a screening question | E77: A question can be marked must-have, and failing it archives the application with a rejection email. | F77: Applications | G77: Hiring manager | H77: Verification log | I77: LinkedIn verification table | J77: General | K77: SHOULD-HAVE | L77: Competitor matrix rule | M77: 1 of 3 studied leaders offer it (LinkedIn); 2 not verified. | N77: Provisional | O77: Verification log | P77: Not built | Q77: Falls short | R77: Derived from the gap table | S77: New insight | T77: is_required exists only. | U77: OK | V77: Source type: LinkedIn verification table | Evidence status: Verification log (page or snippet, not marked per row) | Trace status: NEW INSIGHT
A78: FD-075 | B78: Feature | D78: Pipeline stage per recruiter project | E78: A recruiter moves a saved candidate through stages inside a project. | F78: Hiring workflow | G78: Recruiter | H78: Verification log | I78: LinkedIn verification table | J78: General | K78: SHOULD-HAVE | L78: Competitor matrix rule | M78: 1 of 3 studied leaders offer it (LinkedIn); 2 not verified. | N78: Provisional | O78: Verification log | P78: Not built | Q78: Falls short | R78: Derived from the gap table | S78: New insight | T78: shortlist_entry has no stage. | U78: OK | V78: Source type: LinkedIn verification table | Evidence status: Verification log (page or snippet, not marked per row) | Trace status: NEW INSIGHT
A79: FD-076 | B79: Feature | D79: Company page fields | E79: Employee count range, specialties, headquarters flag, year founded and page verification. | F79: Organisation and admin | G79: Organisation administrator | H79: Verification log | I79: LinkedIn verification table | J79: General | K79: SHOULD-HAVE | L79: Competitor matrix rule | M79: 1 of 3 studied leaders offer it (LinkedIn); 2 not verified. | N79: Provisional | O79: Verification log | P79: Not built | Q79: Falls short | R79: Derived from the gap table | S79: New insight | T79: The register says the field comparison is still to do. | U79: OK | V79: Source type: LinkedIn verification table | Evidence status: Verification log (page or snippet, not marked per row) | Trace status: NEW INSIGHT
A80: FD-077 | B80: Feature | D80: Estimated salary range | E80: The listing shows an estimated range when the employer gives none. | F80: Jobs | G80: Candidate | H80: Verification log | I80: LinkedIn verification table | J80: General | K80: SHOULD-HAVE | L80: Competitor matrix rule | M80: 1 of 3 studied leaders offer it (LinkedIn); 2 not verified. | N80: Provisional | O80: Verification log | P80: Not built | Q80: Falls short | R80: Derived from the gap table | S80: New insight | U80: OK | V80: Source type: LinkedIn verification table | Evidence status: Verification log (page or snippet, not marked per row) | Trace status: NEW INSIGHT
A81: FD-078 | B81: Feature | D81: Append-only audit trail written by the database | E81: Who did which sensitive action to what and when. Nobody can change a row; the database writes the rows for sign-in, views, downloads, exports and licence changes. | F81: Privacy and security | G81: Compliance and privacy officer | H81: Own insight | I81: Capability built in the modules; not shown to users by the studied products | J81: Not observable | K81: MUST-HAVE | L81: Recorded rule | M81: Recorded rule: NFR-07 and decision A8 (history is append-only) | N81: Declared | O81: Own design | P81: Built and tested | Q81: Not compared | R81: No competitor claim | S81: Traced | U81: declared | V81: Class basis: Recorded rule: NFR-07 and decision A8 (history is append-only) | Confidence: Declared (not observable) | Evidence status: Own design (no competitor claim) | Trace status: Traced to requirement
A82: FD-079 | B82: Feature | D82: Consent history | E82: Consent decisions are kept as history with the document version; a withdrawal is a new row. | F82: Privacy and security | G82: Compliance and privacy officer | H82: Own insight | I82: Capability built in the modules; not shown to users by the studied products | J82: Not observable | K82: MUST-HAVE | L82: Recorded rule | M82: Recorded rule: decision A8 (consent history is append-only) | N82: Declared | O82: Own design | P82: Built and tested | Q82: Not compared | R82: No competitor claim | S82: Traced | U82: declared | V82: Class basis: Recorded rule: decision A8 (consent history is append-only) | Confidence: Declared (not observable) | Evidence status: Own design (no competitor claim) | Trace status: Traced to requirement
A83: FD-080 | B83: Feature | D83: Erasure by scrubbing, keeping history | E83: A person is erased through one entry point that scrubs personal text everywhere while counts, money and the audit trail remain. | F83: Privacy and security | G83: Compliance and privacy officer | H83: Own insight | I83: Capability built in the modules; not shown to users by the studied products | J83: Not observable | K83: MUST-HAVE | L83: Recorded rule | M83: Recorded rule: NFR-12 and the team approval of erasure by scrubbing (X7) | N83: Declared | O83: Own design | P83: Built and tested | Q83: Not compared | R83: No competitor claim | S83: Traced | U83: declared | V83: Class basis: Recorded rule: NFR-12 and the team approval of erasure by scrubbing (X7) | Confidence: Declared (not observable) | Evidence status: Own design (no competitor claim) | Trace status: Traced to requirement
A84: FD-081 | B84: Feature | D84: Roles and permissions with dates and scope | E84: A role is granted for a period, optionally for one organisation; one active grant per account, role and organisation. | F84: Organisation and admin | G84: Platform administrator | H84: Own insight | I84: Capability built in the modules; not shown to users by the studied products | J84: Not observable | K84: SHOULD-HAVE | L84: Supporting capability | M84: Supporting capability (not compared with competitors) | N84: Declared | O84: Own design | P84: Built and tested | Q84: Not compared | R84: No competitor claim | S84: Traced | U84: declared | V84: Class basis: Supporting capability (not compared with competitors) | Confidence: Declared (not observable) | Evidence status: Own design (no competitor claim) | Trace status: Traced to requirement
A85: FD-082 | B85: Feature | D85: Row-level security by organisation and by person | E85: The database decides which rows each type of user sees: an organisation reads its own rows, a candidate reads their own, a blocked party sees nothing. | F85: Privacy and security | G85: Compliance and privacy officer | H85: Own insight | I85: Capability built in the modules; not shown to users by the studied products | J85: Not observable | K85: MUST-HAVE | L85: Brief demands | M85: Brief demands: the blocked-party rule (decision A7) and NFR-09 | N85: Declared | O85: Own design | P85: Built and tested | Q85: Not compared | R85: No competitor claim | S85: Traced | U85: declared | V85: Class basis: Brief demands: the blocked-party rule (decision A7) and NFR-09 | Confidence: Declared (not observable) | Evidence status: Own design (no competitor claim) | Trace status: Traced to requirement
A86: FD-083 | B86: Feature | D86: Monthly partitions and stated retention | E86: The largest tables are split by month or by candidate, each with a stated retention period; the audit trail is never dropped. | F86: Platform and scale | G86: Platform operator | H86: Own insight | I86: Capability built in the modules; not shown to users by the studied products | J86: Not observable | K86: MUST-HAVE | L86: Brief demands | M86: Brief demands: partitioning of the largest tables (docs/schema-justification.md); NFR-01 and NFR-02 | N86: Declared | O86: Own design | P86: Built and tested | Q86: Not compared | R86: No competitor claim | S86: Traced | U86: declared | V86: Class basis: Brief demands: partitioning of the largest tables (docs/schema-justification.md); NFR-01 and NFR-02 | Confidence: Declared (not observable) | Evidence status: Own design (no competitor claim) | Trace status: Traced to requirement
A87: FD-084 | B87: Feature | D87: Limits that hold under parallel sessions | E87: Seat, device and session limits, the wallet balance and the one-application rule hold when two sessions act at the same moment. | F87: Platform and scale | G87: Platform operator | H87: Own insight | I87: Capability built in the modules; not shown to users by the studied products | J87: Not observable | K87: MUST-HAVE | L87: Brief demands | M87: Brief demands: licence and concurrency limits enforced by constraint or locking (rule group 2, docs/rule-compliance.md) | N87: Declared | O87: Own design | P87: Built and tested | Q87: Not compared | R87: No competitor claim | S87: Traced | U87: declared | V87: Class basis: Brief demands: licence and concurrency limits enforced by constraint or locking (rule group 2, docs/rule-compliance.md) | Confidence: Declared (not observable) | Evidence status: Own design (no competitor claim) | Trace status: Traced to requirement
A88: FD-085 | B88: Feature | D88: Outside-system exchange log | E88: Every message to or from the nine outside systems is logged with a hash of the body, never the body; a repeated message adds nothing. | F88: Organisation and admin | G88: Integration service | H88: Own insight | I88: Capability built in the modules; not shown to users by the studied products | J88: Not observable | K88: MUST-HAVE | L88: Brief demands | M88: Brief demands: what each of the nine systems must store (docs/integration-boundaries.md) | N88: Declared | O88: Own design | P88: Built and tested | Q88: Not compared | R88: No competitor claim | S88: Traced | U88: declared | V88: Class basis: Brief demands: what each of the nine systems must store (docs/integration-boundaries.md) | Confidence: Declared (not observable) | Evidence status: Own design (no competitor claim) | Trace status: Traced to requirement
A89: FD-086 | B89: Feature | D89: Links to the old systems | E89: Records of the old systems are kept with sync direction, status, last error and source version, for candidates and for jobs. | F89: Organisation and admin | G89: Integration service | H89: Own insight | I89: Capability built in the modules; not shown to users by the studied products | J89: Not observable | K89: MUST-HAVE | L89: Brief demands | M89: Brief demands: a sync direction per field and one conflict rule (docs/integration-boundaries.md); one direction per record is built | N89: Declared | O89: Own design | P89: Built and tested | Q89: Not compared | R89: No competitor claim | S89: Traced | U89: declared | V89: Class basis: Brief demands: a sync direction per field and one conflict rule (docs/integration-boundaries.md); one direction per record is built | Confidence: Declared (not observable) | Evidence status: Own design (no competitor claim) | Trace status: Traced to requirement
A90: FD-087 | B90: Feature | D90: Append-only credit ledger with a balance check | E90: Credits move only through an append-only ledger; the wallet balance is a copy that a function can check against the ledger. | F90: Licences, subscriptions and wallet | G90: Organisation administrator | H90: Own insight | I90: Capability built in the modules; not shown to users by the studied products | J90: Not observable | K90: SHOULD-HAVE | L90: Supporting capability | M90: Supporting capability: how credits (a compared feature) stay correct | N90: Declared | O90: Own design | P90: Built and tested | Q90: Not compared | R90: No competitor claim | S90: Traced | U90: declared | V90: Class basis: Supporting capability: how credits (a compared feature) stay correct | Confidence: Declared (not observable) | Evidence status: Own design (no competitor claim) | Trace status: Traced to requirement
A91: FD-088 | B91: Feature | D91: Payment messages stored once | E91: Payments are stored as the gateway's messages; a repeated message adds nothing and a refund cannot exceed its charge. No card data is stored. | F91: Licences, subscriptions and wallet | G91: Organisation administrator | H91: Own insight | I91: Capability built in the modules; not shown to users by the studied products | J91: Not observable | K91: SHOULD-HAVE | L91: Supporting capability | M91: Supporting capability (not compared with competitors) | N91: Declared | O91: Own design | P91: Built and tested | Q91: Not compared | R91: No competitor claim | S91: Traced | U91: declared | V91: Class basis: Supporting capability (not compared with competitors) | Confidence: Declared (not observable) | Evidence status: Own design (no competitor claim) | Trace status: Traced to requirement
... A126: FD-123 | B126: Feature | D126: Hiring line: Gig work | E126: Short tasks with a window and a price, one-way bids and outside fulfilment. | F126: Gig | G126: Gig worker | H126: Domain primer | I126: Domain Primer sheet: Gig work | J126: Not observable | K126: SHOULD-HAVE | L126: Domain primer | M126: Domain Primer: a hiring line the platform serves (not compared with competitors) | N126: Declared | O126: Own design | P126: Built | Q126: Not compared | R126: No competitor claim | S126: Traced | U126: declared | V126: Source type: Domain Primer | Class basis: Domain Primer: a hiring line the platform serves (not compared with competitors) | Confidence: Declared (not observable) | Evidence status: Own design (no competitor claim) | Trace status: Traced to requirement
A127: FD-124 | B127: Capability | C127: FD-018 | D127: A candidate can hold several emails and phone numbers, one primary per type, no duplicates per candidate, vali... | E127: A candidate can hold several emails and phone numbers, one primary per type, no duplicates per candidate, valid shapes only. | F127: Profile | G127: Candidate | H127: Functional requirement | I127: FR-P02 | J127: General | K127: MUST-HAVE | L127: Inherited from parent feature | M127: Part of FD-018: Personal details (date of birth, gender, address, contacts) | N127: Firm | O127: Known | P127: Built and tested | Q127: Matches | R127: Inherited from FD-018 | S127: Traced | U127: inherited | V127: Class basis: Inherited from FD-018 | Trace status: Traced to requirement
A128: FD-125 | B128: Capability | C128: FD-029 | D128: Employers and recruiters can bookmark candidates, and removals are kept as history | E128: Employers and recruiters can bookmark candidates, and removals are kept as history. | F128: Hiring workflow | G128: Recruiter | H128: Functional requirement | I128: FR-P09 | J128: General | K128: MUST-HAVE | L128: Inherited from parent feature | M128: Part of FD-029: Folders of accessed or saved candidates | N128: Firm | O128: Public | P128: Built | Q128: Matches | R128: Inherited from FD-029 | S128: Traced | U128: inherited | V128: Class basis: Inherited from FD-029 | Trace status: Traced to requirement
A129: FD-126 | B129: Capability | C129: FD-029 | D129: Recruiters build shortlists of candidates for a requirement | E129: Recruiters build shortlists of candidates for a requirement. | F129: Hiring workflow | G129: Recruiter | H129: Functional requirement | I129: FR-J11 | J129: General | K129: MUST-HAVE | L129: Inherited from parent feature | M129: Part of FD-029: Folders of accessed or saved candidates | N129: Firm | O129: Public | P129: Built and tested | Q129: Matches | R129: Inherited from FD-029 | S129: Traced | U129: inherited | V129: Class basis: Inherited from FD-029 | Trace status: Traced to requirement
A130: FD-127 | B130: Capability | C130: FD-032 | D130: A user registers devices under a licence up to the device limit | E130: A user registers devices under a licence up to the device limit; a revoked device is recorded with who and why and stays revoked. | F130: Licences, subscriptions and wallet | G130: Organisation administrator | H130: Functional requirement | I130: FR-L03 | J130: General | K130: SHOULD-HAVE | L130: Inherited from parent feature | M130: Part of FD-032: Team users, seats, device limits | N130: Provisional | O130: Public | P130: Built and tested | Q130: Exceeds | R130: Inherited from FD-032 | S130: Traced | U130: inherited | V130: Class basis: Inherited from FD-032 | Trace status: Traced to requirement
A131: FD-128 | B131: Capability | C131: FD-032 | D131: Sessions keep device, start, last activity and end | E131: Sessions keep device, start, last activity and end; finished sessions are kept 90 days by month; expired and revoked sessions are not counted. | F131: Licences, subscriptions and wallet | G131: Organisation administrator | H131: Functional requirement | I131: FR-L06 | J131: General | K131: SHOULD-HAVE | L131: Inherited from parent feature | M131: Part of FD-032: Team users, seats, device limits | N131: Provisional | O131: Public | P131: Built and tested | Q131: Exceeds | R131: Inherited from FD-032 | S131: Traced | U131: inherited | V131: Class basis: Inherited from FD-032 | Trace status: Traced to requirement
A132: FD-129 | B132: Capability | C132: FD-032 | D132: Revoking a device or a session is audited, and ending a seat, a membership or a licence ends what depended on ... | E132: Revoking a device or a session is audited, and ending a seat, a membership or a licence ends what depended on it. | F132: Licences, subscriptions and wallet | G132: Organisation administrator | H132: Functional requirement | I132: FR-L07 | J132: General | K132: SHOULD-HAVE | L132: Inherited from parent feature | M132: Part of FD-032: Team users, seats, device limits | N132: Provisional | O132: Public | P132: Built and tested | Q132: Exceeds | R132: Inherited from FD-032 | S132: Traced | U132: inherited | V132: Class basis: Inherited from FD-032 | Trace status: Traced to requirement
A133: FD-130 | B133: Capability | C133: FD-032 | D133: Only the licence functions can end a session or write its history, and only a role with the grant can call the... | E133: Only the licence functions can end a session or write its history, and only a role with the grant can call them. | F133: Licences, subscriptions and wallet | G133: Organisation administrator | H133: Functional requirement | I133: FR-L08 | J133: General | K133: SHOULD-HAVE | L133: Inherited from parent feature | M133: Part of FD-032: Team users, seats, device limits | N133: Provisional | O133: Public | P133: Built and tested | Q133: Exceeds | R133: Inherited from FD-032 | S133: Traced | U133: inherited | V133: Class basis: Inherited from FD-032 | Trace status: Traced to requirement
A134: FD-131 | B134: Capability | C134: FD-033 | D134: Registration and tax numbers are kept apart as Sensitive data, with country and type, and each type states the... | E134: Registration and tax numbers are kept apart as Sensitive data, with country and type, and each type states the format the number must match. | F134: Organisation and admin | G134: Organisation administrator | H134: Functional requirement | I134: FR-O03 | J134: General | K134: SHOULD-HAVE | L134: Inherited from parent feature | M134: Part of FD-033: Company details, locations, tax ids, verification | N134: Provisional | O134: Known | P134: Built and tested | Q134: Matches | R134: Inherited from FD-033 | S134: Traced | U134: inherited | V134: Class basis: Inherited from FD-033 | Trace status: Traced to requirement
A135: FD-132 | B135: Capability | C135: FD-033 | D135: Verification of an organisation is an append-only history | E135: Verification of an organisation is an append-only history; a repeated provider event adds no second row. | F135: Organisation and admin | G135: Organisation administrator | H135: Functional requirement | I135: FR-O04 | J135: General | K135: SHOULD-HAVE | L135: Inherited from parent feature | M135: Part of FD-033: Company details, locations, tax ids, verification | N135: Provisional | O135: Known | P135: Built and tested | Q135: Matches | R135: Inherited from FD-033 | S135: Traced | U135: inherited | V135: Class basis: Inherited from FD-033 | Trace status: Traced to requirement
A136: FD-133 | B136: Capability | C136: FD-033 | D136: An email domain belongs to one active organisation, for matching recruiter addresses | E136: An email domain belongs to one active organisation, for matching recruiter addresses. | F136: Organisation and admin | G136: Organisation administrator | H136: Functional requirement | I136: FR-O07 | J136: General | K136: SHOULD-HAVE | L136: Inherited from parent feature | M136: Part of FD-033: Company details, locations, tax ids, verification | N136: Provisional | O136: Known | P136: Built and tested | Q136: Matches | R136: Inherited from FD-033 | S136: Traced | U136: inherited | V136: Class basis: Inherited from FD-033 | Trace status: Traced to requirement
A137: FD-134 | B137: Capability | C137: FD-037 | D137: A requirement lists required and preferred skills, qualifications and locations | E137: A requirement lists required and preferred skills, qualifications and locations. | F137: Jobs | G137: Hiring manager | H137: Functional requirement | I137: FR-J03 | J137: General | K137: SHOULD-HAVE | L137: Inherited from parent feature | M137: Part of FD-037: Job posting with skills, qualifications, locations, experience range, salary | N137: Provisional | O137: Known | P137: Built and tested | Q137: Matches | R137: Inherited from FD-037 | S137: Traced | U137: inherited | V137: Class basis: Inherited from FD-037 | Trace status: Traced to requirement
A138: FD-135 | B138: Capability | C138: FD-040 | D138: An application keeps its current status and an append-only history of every change | E138: An application keeps its current status and an append-only history of every change. | F138: Applications | G138: Candidate | H138: Functional requirement | I138: FR-J09 | J138: General | K138: MUST-HAVE | L138: Inherited from parent feature | M138: Part of FD-040: Application status tracking | N138: Firm | O138: Known | P138: Built and tested | Q138: Exceeds | R138: Inherited from FD-040 | S138: Traced | U138: inherited | V138: Class basis: Inherited from FD-040 | Trace status: Traced to requirement
... A179: FD-176 | B179: Capability | C179: FD-099 | D179: A staffing agency posts for a client only through an active link, and only an organisation of type staffing ag... | E179: A staffing agency posts for a client only through an active link, and only an organisation of type staffing agency can be the agency. | F179: Jobs | G179: Recruiter | H179: Functional requirement | I179: FR-O06 | J179: General | K179: SHOULD-HAVE | L179: Inherited from parent feature | M179: Part of FD-099: Agency posts for a client | N179: Provisional | O179: Own design | P179: Built and tested | Q179: Not compared | R179: Inherited from FD-099 | S179: Traced | U179: inherited | V179: Class basis: Inherited from FD-099 | Evidence status: Own design (no competitor claim) | Trace status: Traced to requirement

Sheet Coverage matrix
A1: Output document (draft, deliverable c): the competitor coverage matrix, in the original column layout (one column per competitor).
A3: ID | B3: Feature | C3: Category | D3: Scope | E3: Naukri | F3: Monster | G3: LinkedIn | H3: Naukri Campus | I3: Leaders studied | J3: Offering | K3: Not verified | L3: Rule-based class | M3: Confidence | N3: Our coverage | O3: Verdict
A4: FD-001 | B4: Resume headline and profile summary | C4: Profile | D4: General | E4: Yes | F4: Partial | G4: Yes | H4: Partial | I4: 3 | J4: 3 | K4: 0 | L4: MUST-HAVE | M4: Firm | N4: Built and tested | O4: Matches
A5: FD-002 | B5: Employment history with designation, organisation, duration, description | C5: Profile | D5: General | E5: Yes | F5: Partial | G5: Yes | H5: Partial | I5: 3 | J5: 3 | K5: 0 | L5: MUST-HAVE | M5: Firm | N5: Built and tested | O5: Matches
A6: FD-003 | B6: Education | C6: Profile | D6: General | E6: Yes | F6: Partial | G6: Yes | H6: Yes | I6: 3 | J6: 3 | K6: 0 | L6: MUST-HAVE | M6: Firm | N6: Built and tested | O6: Matches
A7: FD-004 | B7: Key skills | C7: Profile | D7: General | E7: Yes | F7: Partial | G7: Yes | H7: Yes | I7: 3 | J7: 3 | K7: 0 | L7: MUST-HAVE | M7: Firm | N7: Built and tested | O7: Exceeds
A8: FD-005 | B8: IT skills with software version | C8: Profile | D8: General | E8: Partial | F8: No | G8: No | H8: No | I8: 3 | J8: 1 | K8: 0 | L8: DIFFERENTIATOR | M8: Firm | N8: Built and tested | O8: Matches
A9: FD-006 | B9: Languages | C9: Profile | D9: General | E9: No | F9: Not verified | G9: Yes | H9: No | I9: 3 | J9: 1 | K9: 1 | L9: SHOULD-HAVE | M9: Provisional | N9: Built and tested | O9: Exceeds
A10: FD-007 | B10: Certifications and licences | C10: Profile | D10: General | E10: Partial | F10: Partial | G10: Yes | H10: Not verified | I10: 3 | J10: 3 | K10: 0 | L10: MUST-HAVE | M10: Firm | N10: Built and tested | O10: Matches
A11: FD-008 | B11: Projects | C11: Profile | D11: General | E11: Yes | F11: No | G11: Yes | H11: Not verified | I11: 3 | J11: 2 | K11: 0 | L11: SHOULD-HAVE | M11: Firm | N11: Built and tested | O11: Matches
A12: FD-009 | B12: Accomplishments: publications, patents, work samples | C12: Profile | D12: General | E12: Yes | F12: No | G12: Yes | H12: No | I12: 3 | J12: 2 | K12: 0 | L12: SHOULD-HAVE | M12: Firm | N12: Built and tested | O12: Matches
A13: FD-010 | B13: Volunteering and organisations | C13: Profile | D13: General | E13: No | F13: No | G13: Yes | H13: No | I13: 3 | J13: 1 | K13: 0 | L13: DIFFERENTIATOR | M13: Firm | N13: Built and tested | O13: Matches
A14: FD-011 | B14: Recommendations and endorsements | C14: Profile | D14: General | E14: No | F14: No | G14: Yes | H14: No | I14: 3 | J14: 1 | K14: 0 | L14: DIFFERENTIATOR | M14: Firm | N14: Not built | O14: Falls short
A15: FD-012 | B15: Courses | C15: Profile | D15: General | E15: Not verified | F15: No | G15: Yes | H15: Not verified | I15: 3 | J15: 1 | K15: 1 | L15: SHOULD-HAVE | M15: Provisional | N15: Built | O15: Exceeds
... A126: FD-123 | B126: Hiring line: Gig work | C126: Gig | D126: Not observable | E126: Not verified | F126: Not verified | G126: Not verified | H126: Not verified | I126: 0 | J126: 0 | K126: 0 | L126: declared | M126: Declared (not observable) | N126: Built | O126: Not compared
B128: Counts (live formulas)
B129: Yes | E129: =COUNTIF(E$4:E$126,"Yes") | F129: =COUNTIF(F$4:F$126,"Yes") | G129: =COUNTIF(G$4:G$126,"Yes") | H129: =COUNTIF(H$4:H$126,"Yes")
B130: Partial | E130: =COUNTIF(E$4:E$126,"Partial") | F130: =COUNTIF(F$4:F$126,"Partial") | G130: =COUNTIF(G$4:G$126,"Partial") | H130: =COUNTIF(H$4:H$126,"Partial")
B131: No | E131: =COUNTIF(E$4:E$126,"No") | F131: =COUNTIF(F$4:F$126,"No") | G131: =COUNTIF(G$4:G$126,"No") | H131: =COUNTIF(H$4:H$126,"No")
B132: Not verified | E132: =COUNTIF(E$4:E$126,"Not verified") | F132: =COUNTIF(F$4:F$126,"Not verified") | G132: =COUNTIF(G$4:G$126,"Not verified") | H132: =COUNTIF(H$4:H$126,"Not verified")

Sheet Competitors
A1: The competing products that were studied.
A3: Competitor | B3: Why studied | C3: Verified by and when | D3: What was studied | E3: Own pages listed | F3: Read (16 Oct) | G3: Search summary only (16 Oct) | H3: Not readable (16 Oct) | I3: Yes | J3: Partial | K3: No | L3: Not verified | M3: Limits of the evidence
A4: Naukri | B4: Largest Indian job board; employer search product called Resdex. Required: studied. | C4: Yash, 15 October 2026 (verification log) | D4: Company help and blog pages; search summaries when pages refused download | E4: 5 | F4: 0 | G4: 5 | H4: 2 | I4: 29 | J4: 9 | K4: 6 | L4: 28 | M4: Pages refused direct download (403) on 16 October; cells rest on search summaries.
A5: Monster | B5: Global job board; resume search and credits. Required: studied. | C5: Ishaan, 15 October 2026 (verification log) | D5: Public Monster pages and help centre | E5: 9 | F5: 3 | G5: 1 | H5: 0 | I5: 18 | J5: 9 | K5: 13 | L5: 32 | M5: Sign-in, profile editor and employer dashboard cannot be opened without an account; Monster India is now Foundit.
A6: LinkedIn | B6: Professional network with Recruiter and Recruiter Lite. Required: studied. | C6: Prabhav, 15 October 2026 (verification log); 16 October re-read of the help pages | D6: LinkedIn Help pages for members and Recruiter | E6: 4 | F6: 7 | G6: 6 | H6: 0 | I6: 43 | J6: 14 | K6: 8 | L6: 7 | M6: Some pages are search summaries only; university guides are third-party.
A7: Naukri Campus | B7: Campus and fresher hiring product. Required: studied. | C7: Checked only where public pages describe it | D7: Older mailers and student pages | E7: 2 | F7: 0 | G7: 1 | H7: 1 | I7: 3 | J7: 0 | K7: 0 | L7: 1 | M7: Main pages not readable (403); only one leader for campus features.

Sheet NFR register
A1: Output document (draft, deliverable c, Step 04): the 20 NFRs from Talentra-Requirements.xlsx, plus NFR-21 to NFR-26, which are my proposals (status Proposed): NFR-21 and NFR-22 for the Compliance and Accessibility gaps, NFR-23 to NFR-26 for load time, data quality, concurrency and cost, each from facts already in the project. All six are left out of the Step 04 playbook checks. Columns follow the nfr table. Numeric targets are filled only where the requirement states a number; derivation and the measured-by kind are my reading and need a person to confirm.
A3: nfr_id | B3: study_id | C3: category | D3: requirement_statement | E3: source_reference | F3: metric | G3: unit | H3: comparator | I3: target_value | J3: target_text | K3: target_status | L3: test_method | M3: measured_by | N3: evidence_reference | O3: derived_from | P3: volume_basis | Q3: regulation_name | R3: our_status | S3: status_detail
A4: NFR-01 | B4: FDS-01 | C4: Scale | D4: The design holds 1 million candidates, 1 million job requirements and 100 million applications. | E4: Requirements workbook, Non-Functional Requirements, NFR-01 | F4: Candidates held | G4: candidates | H4: At least | I4: 1000000 | J4: 1M candidates, 100M applications | K4: Set | L4: Row estimates per table; partitioning; 11 MB of disk per 1,000 candidates measured. Full load needs a larger machine (Phase 5) | M4: Document check | O4: Volumes | P4: 1M candidates and 100M applications from the brief | R4: Designed | S4: Designed. Proven to 50,000 candidates and 250,000 applications so far
A5: NFR-02 | B5: FDS-01 | C5: Scale | D5: The largest tables are partitioned from day one: applications by candidate, event tables by month. | E5: Requirements workbook, Non-Functional Requirements, NFR-02 | F5: Partitioned tables | G5: tables | H5: At least | I5: 23 | J5: 23 partitioned tables | K5: Set | L5: 530 partitions; partition tests; 16 hash partitions locally, 64 in production | M5: Automated test | O5: Team decision | R5: Built and tested | S5: Built and tested
A6: NFR-03 | B6: FDS-01 | C6: Performance | D6: Candidate search by skill, the employer pipeline and my-applications views return within agreed times at full scale. | E6: Requirements workbook, Non-Functional Requirements, NFR-03 | F6: Response time of the three main views | J6: To be set from measurements | K6: To be set | L6: EXPLAIN ANALYZE at scale; both partition orders compared | M6: Query plan | O6: Not yet derived | R6: Planned | S6: Planned (B71 to B73)
A7: NFR-04 | B7: FDS-01 | C7: Performance | D7: Indexes exist for every foreign key to a business table; lookups are not indexed because they are never deleted. | E7: Requirements workbook, Non-Functional Requirements, NFR-04 | F7: Business foreign keys without an index | G7: foreign keys | H7: At most | I7: 0 | J7: No unindexed business foreign key | K7: Set | L7: fk_index rule in the generator plus 14 partial indexes on nullable keys (IX1); two documented exceptions: audit keys to user_account (SO25) and notification_delivery.notification_template_id (IX2); a catalogue test in tests/extra_security.sql fails on any other unindexed key | M7: Automated test | O7: Team decision | R7: Built and tested | S7: Built and tested (review round 7)
A8: NFR-05 | B8: FDS-01 | C8: Data integrity | D8: Business rules are enforced by the database: keys, 633 check rules, unique and exclusion rules, composite foreign keys. | E8: Requirements workbook, Non-Functional Requirements, NFR-05 | F8: Business rules that exist only in application code | G8: rules | H8: At most | I8: 0 | J8: No rule only in application code | K8: Set | L8: 2066 of 2066 constraint tests pass | M8: Automated test | O8: Team decision | R8: Built and tested | S8: Built and tested
A9: NFR-06 | B9: FDS-01 | C9: Data integrity | D9: Every foreign key has an explicit delete rule; business data is never silently cascaded away. | E9: Requirements workbook, Non-Functional Requirements, NFR-06 | F9: Foreign keys without an explicit delete rule | J9: RESTRICT by default | K9: Set | L9: docs/modules/*/relationships.md; key tests | M9: Automated test | O9: Team decision | R9: Built | S9: Built
A10: NFR-07 | B10: FDS-01 | C10: Auditability | D10: Every row records who and when; history tables are append-only and refuse update and delete. | E10: Requirements workbook, Non-Functional Requirements, NFR-07 | F10: Business tables recording who and when | J10: All business tables | K10: Set | L10: Audit columns; append-only triggers; append-only tests | M10: Automated test | O10: Team decision | R10: Built and tested | S10: Built and tested
A11: NFR-08 | B11: FDS-01 | C11: Auditability | D11: Query timing is observable. | E11: Requirements workbook, Non-Functional Requirements, NFR-08 | F11: Query timing observable | J11: pg_stat_statements on | K11: Set | L11: schema/00_extensions.sql | M11: Document check | O11: Team decision | R11: Built | S11: Built
A12: NFR-09 | B12: FDS-01 | C12: Security | D12: Row-level security, roles and permissions on tables. | E12: Requirements workbook, Non-Functional Requirements, NFR-09 | F12: Access rules per role | J12: Least privilege: default deny, no policy that is simply true for the application role | K12: Set | L12: schema/10_security.sql from tools/rules_security.py; docs/security/ (roles, policy catalogue, threat model, PII handling, design note); tests/extra_security.sql | M12: Automated test | O12: Team decision | R12: Built and tested | S12: Built and tested (16 October 2026): four service roles, row-level security on 120 tables with 376 policies, 227 access tests as ordinary roles; the policy cost at full scale is measured in Phase 5
A13: NFR-10 | B13: FDS-01 | C13: Security | D13: Secrets stay out of the repository; the database port is never public; remote access by SSH tunnel. | E13: Requirements workbook, Non-Functional Requirements, NFR-10 | F13: Secrets kept out of the repository | J13: No .env, key or brief in git | K13: Set | L13: .gitignore, PR template checklist, README | M13: Review | O13: Team decision | R13: Built | S13: Built for the repository; hosting rules recorded
A14: NFR-11 | B14: FDS-01 | C14: Privacy | D14: Every column has a sensitivity class (Public, Internal, Personal, Sensitive); identity numbers and card data are never stored. | E14: Requirements workbook, Non-Functional Requirements, NFR-11 | F14: Columns without a sensitivity class | G14: columns | H14: At most | I14: 0 | J14: All columns classed | K14: Set | L14: docs/data-dictionary.csv, built by tools/build_data_dictionary.py | M14: Document check | O14: Team decision | R14: Built | S14: Built: every column classed
A15: NFR-12 | B15: FDS-01 | C15: Privacy | D15: Personal data can be erased on request without breaking history, and event data has a retention period. | E15: Requirements workbook, Non-Functional Requirements, NFR-12 | F15: Retention of event data | G15: months | H15: At most | I15: 12 | J15: Erasure function; 12 months for events | K15: Set | L15: erase_candidate() and tests; monthly partitions dropped by month; docs/security/pii-handling.md | M15: Automated test | O15: Team decision | R15: Built | S15: Built: erase_candidate() reached only through talentra_request_erasure() (the person or a user administrator); the inactivity rule and the retention scheduler are planned
A16: NFR-13 | B16: FDS-01 | C16: Portability | D16: The same database runs on macOS, Windows and Linux from one codebase. | E16: Requirements workbook, Non-Functional Requirements, NFR-13 | F16: Systems the database runs on | J16: One docker compose file | K16: Set | L16: docker-compose.yml, docs/setup.md | M16: Document check | O16: Team decision | R16: Built and tested | S16: Built and tested on Mac, run by teammates on Windows
A17: NFR-14 | B17: FDS-01 | C17: Maintainability | D17: One diagram file is the source of the model; the SQL is generated and never edited by hand; rules that a diagram cannot show sit in one reviewed list. | E17: Requirements workbook, Non-Functional Requirements, NFR-14 | F17: Sources of truth for the model | J17: One source of truth | K17: Set | L17: tools/build_schema.py, docs/dbml/talentra.dbml | M17: Document check | O17: Team decision | R17: Built | S17: Built
A18: NFR-15 | B18: FDS-01 | C18: Maintainability | D18: Naming standards: snake_case, singular table names, id and table_id keys, no reserved words. | E18: Requirements workbook, Non-Functional Requirements, NFR-15 | F18: Naming violations | G18: violations | H18: At most | I18: 0 | J18: 0 violations | K18: Set | L18: docs/schema.md: no name clashes with reserved words | M18: Automated test | O18: Team decision | R18: Built | S18: Built and checked
A19: NFR-16 | B19: FDS-01 | C19: Time and language | D19: All timestamps are stored in UTC; names can be in any script. | E19: Requirements workbook, Non-Functional Requirements, NFR-16 | F19: Timestamps stored in UTC | J19: timestamptz in UTC; UTF-8 | K19: Set | L19: Standards in docs/modules/*/columns.md | M19: Document check | O19: Team decision | R19: Built | S19: Built
A20: NFR-17 | B20: FDS-01 | C20: Reproducibility | D20: Anyone can rebuild the empty database and load repeatable demo data in minutes. | E20: Requirements workbook, Non-Functional Requirements, NFR-17 | F20: Rebuild time of the empty database | G20: seconds | H20: At most | I20: 120 | J20: Rebuild under 2 minutes for the empty database; 50,000 candidates with every module in about 5 minutes (measured 16 October 2026) | K20: Set | L20: schema/ runs on first start; seed/reference/ then seed/demo_sample.sql | M20: Automated test | O20: Team decision | R20: Built and tested | S20: Built and tested
A21: NFR-18 | B21: FDS-01 | C21: Quality assurance | D21: A test suite tries to break every important rule and runs against a scratch database. | E21: Requirements workbook, Non-Functional Requirements, NFR-18 | F21: Failing tests before a merge | G21: tests | H21: At most | I21: 0 | J21: All tests pass before every merge | K21: Set | L21: tests/constraint_tests.sql | M21: Automated test | O21: Team decision | R21: Built | S21: Built: 2066 of 2066 pass
A22: NFR-19 | B22: FDS-01 | C22: Availability and recovery | D22: Backups, restore tests and a recovery target. | E22: Requirements workbook, Non-Functional Requirements, NFR-19 | F22: Recovery target | J22: To be set | K22: To be set | L22: Not built yet | M22: Not yet defined | O22: Not yet derived | R22: Planned | S22: Planned (Phase 5)
A23: NFR-20 | B23: FDS-01 | C23: Review process | D23: No design is approved by its author; every change goes through a pull request with an owner. | E23: Requirements workbook, Non-Functional Requirements, NFR-20 | F23: Pieces approved by their own author | J23: Every piece reviewed by someone other than its author | K23: Set | L23: GitHub board, CODEOWNERS, pull request template, docs/decisions.md | M23: Review | O23: Team decision | R23: Partly met | S23: Partly met: Phase 1 pieces were validated by teammates; the 16 October work was closed by the lead after an independent review
A24: NFR-21 | B24: FDS-01 | C24: Compliance | D24: Personal data is handled as the DPDP Act 2023 requires: consent is recorded, a person can have their data erased on request, and the time allowed to act is fixed. | E24: Requirements workbook, Non-Functional Requirements, NFR-21 | F24: Data requests handled within the legal period | J24: To be set with legal review | K24: To be set | L24: Not defined yet. NFR-12 already covers erasure; consent and the legal time limit need their own tests. | M24: Not yet defined | O24: Regulation | Q24: DPDP Act 2023 | R24: Proposed | S24: Proposed: not yet in the requirements workbook; needs team approval
A25: NFR-22 | B25: FDS-01 | C25: Accessibility | D25: Any user interface meets a stated accessibility standard so people with disabilities can use it. | E25: Requirements workbook, Non-Functional Requirements, NFR-22 | F25: Accessibility standard met | J25: To be set; the team decides whether a user interface is in scope | K25: To be set | L25: Not defined yet. The database has no user interface today. | M25: Not yet defined | O25: Not yet derived | R25: Proposed | S25: Proposed: not yet in the requirements workbook; needs team approval
A26: NFR-23 | B26: FDS-01 | C26: Scale | D26: Loading 1 million candidates with all their related rows finishes within a stated time and can resume after a failure. | E26: Requirements workbook, Non-Functional Requirements, NFR-23 | F26: Time to load 1 million candidates | G26: hours | H26: At most | I26: 3 | J26: At most 3 hours for 1M candidates | K26: Set | L26: Load test on the server. 200,000 candidates loaded in 22 minutes on 16 October; the 1M figure is an estimate until that run is done. | M26: Load test | O26: Volumes | P26: 1M candidates; 200,000 loaded in 22 minutes | R26: Proposed | S26: Proposed: not yet in the requirements workbook; needs team approval
A27: NFR-24 | B27: FDS-01 | C27: Data quality | D27: A row with a missing or invalid required value is never loaded; it is rejected with a reason. | E27: Requirements workbook, Non-Functional Requirements, NFR-24 | F27: Incomplete rows loaded | G27: rows | H27: At most | I27: 0 | J27: 0 incomplete rows loaded | K27: Set | L27: Ingestion pipeline: rejected rows go to ingest.reject with a reason; validation checks run after each load. | M27: Automated test | O27: Team decision | R27: Proposed | S27: Proposed: not yet in the requirements workbook; needs team approval
A28: NFR-25 | B28: FDS-01 | C28: Concurrency | D28: When many users act at the same time, limits such as seats, licences and queue claims still hold and nothing is double-booked. | E28: Requirements workbook, Non-Functional Requirements, NFR-25 | F28: Failed concurrency tests | G28: tests | H28: At most | I28: 0 | J28: 0 failed concurrency tests | K28: Set | L28: The concurrency scripts for sourcing, notifications and security pass. | M28: Automated test | O28: Team decision | R28: Proposed | S28: Proposed: not yet in the requirements workbook; needs team approval
A29: NFR-26 | B29: FDS-01 | C29: Cost | D29: The hosting spend for the project stays inside the budget. | E29: Requirements workbook, Non-Functional Requirements, NFR-26 | F29: AWS credit spent | G29: USD | H29: At most | I29: 130 | J29: At most 130 USD of AWS credit | K29: Set | L29: Not measured yet: check the AWS billing page and stop the server when it is not in use. | M29: Document check | O29: Team decision | R29: Proposed | S29: Proposed: not yet in the requirements workbook; needs team approval

Sheet Requirements
A1: Output document (draft, deliverable c, Step 01): the 108 functional requirements from Talentra-Requirements.xlsx in the column order of the requirement table. Source is Not recorded because the workbook does not say which sentence of the brief each requirement came from. Actor and priority are worked out from the features that implement the requirement (the most common persona; the strongest class) and need a person to confirm.
A3: requirement_id | B3: study_id | C3: module | D3: requirement_statement | E3: source_type | F3: source_reference | G3: actor | H3: priority | I3: priority_basis | J3: ambiguity_note | K3: our_status | L3: status_detail | M3: evidence_reference | N3: tables_used
A4: FR-P01 | B4: FDS-01 | C4: Profile | D4: Each user account has at most one candidate profile, with a legal name, an optional Latin spelling, and work status. | E4: Not recorded | G4: Candidate | H4: MUST-HAVE | I4: Derived from features | K4: Built and tested | L4: Built and tested | M4: Unique rule on user account; name and Latin-name checks; Profile tests | N4: candidate_profile
A5: FR-P02 | B5: FDS-01 | C5: Profile | D5: A candidate can hold several emails and phone numbers, one primary per type, no duplicates per candidate, valid shapes only. | E5: Not recorded | G5: Candidate | H5: MUST-HAVE | I5: Derived from features | K5: Built and tested | L5: Built and tested | M5: Partial unique rules, email and phone checks; Profile review tests | N5: candidate_contact
A6: FR-P03 | B6: FDS-01 | C6: Profile | D6: A candidate records addresses, education, work experience, skills with proficiency, languages with read, write and speak levels, projects, certifications and accomplishments. | E6: Not recorded | G6: Candidate | H6: MUST-HAVE | I6: Derived from features | K6: Built and tested | L6: Built and tested | M6: Tables, keys and checks; demo data of 50,000 candidates | N6: candidate_address, candidate_education, candidate_work_experience, candidate_skill, candidate_language, candidate_project, candidate_certification, candidate_accomplishment
A7: FR-P04 | B7: FDS-01 | C7: Profile | D7: A candidate keeps several resumes, one default, built from templates; every change is a new append-only version. | E7: Not recorded | G7: Candidate | H7: MUST-HAVE | I7: Derived from features | K7: Built and tested | L7: Built and tested | M7: One-default rule; append-only guard on resume_version | N7: resume, resume_version, resume_template
A8: FR-P05 | B8: FDS-01 | C8: Profile | D8: A candidate states job preferences: employment type, work mode, cities and roles. | E8: Not recorded | G8: Candidate | H8: MUST-HAVE | I8: Derived from features | K8: Built and tested | L8: Built and tested | M8: One preference row per candidate rule | N8: candidate_job_preference, candidate_job_preference_city, candidate_job_preference_role
A9: FR-P06 | B9: FDS-01 | C9: Profile | D9: The system keeps a profile completion score and its history with the rule version used. | E9: Not recorded | G9: Candidate | H9: MUST-HAVE | I9: Derived from features | K9: Built | L9: Built | M9: Append-only history table | N9: profile_completion_score_history
A10: FR-P07 | B10: FDS-01 | C10: Profile | D10: Identity verification outcome is stored (status, document type, provider reference), never the identity number or documents. | E10: Not recorded | G10: Candidate | H10: SHOULD-HAVE | I10: Derived from features | K10: Built and tested | L10: Built and tested | M10: Unique provider reference; delete rule RESTRICT | N10: candidate_identity_verification
A11: FR-P08 | B11: FDS-01 | C11: Profile | D11: Who viewed a candidate profile, and when, is recorded for the candidate and for credit charging. | E11: Not recorded | G11: Recruiter | H11: MUST-HAVE | I11: Derived from features | K11: Built and tested | L11: Built and tested | M11: Monthly partitions; exclusion rule on overlapping access grants | N11: profile_view_event, profile_access_grant
A12: FR-P09 | B12: FDS-01 | C12: Profile | D12: Employers and recruiters can bookmark candidates, and removals are kept as history. | E12: Not recorded | G12: Recruiter | H12: MUST-HAVE | I12: Derived from features | K12: Built | L12: Built | M12: Tables and keys | N12: candidate_bookmark, candidate_bookmark_history
A13: FR-P10 | B13: FDS-01 | C13: Profile | D13: Each candidate has one referral code and can be referred by another candidate's code, never their own. | E13: Not recorded | G13: Candidate | H13: SHOULD-HAVE | I13: Derived from features | K13: Built and tested | L13: Built and tested | M13: Self-referral trigger test | N13: referral_code
A14: FR-P11 | B14: FDS-01 | C14: Profile | D14: Personal data can be erased by scrubbing the personal fields while the row and its history stay valid. | E14: Not recorded | G14: Compliance and privacy officer | H14: MUST-HAVE | I14: Derived from features | K14: Built and tested | L14: Built and tested | M14: erase_candidate() run by a dedicated role; the erased_at rule refuses personal data on an erased profile | N14: candidate_profile (erased_at)
A15: FR-P12 | B15: FDS-01 | C15: Profile | D15: Suspected duplicate profiles are linked with a review status. | E15: Not recorded | G15: Platform administrator | H15: DIFFERENTIATOR | I15: Derived from features | K15: Built and tested | L15: Built and tested | M15: Each pair stored once | N15: candidate_duplicate_link
... A111: FR-X03 | B111: FDS-01 | C111: Cross module | D111: Wallet and payments belong to the Subscriptions module. | E111: Not recorded | G111: Organisation administrator | H111: SHOULD-HAVE | I111: Derived from features | K111: Built and tested | L111: Built and tested | M111: docs/modules/subscriptions | N111: wallet, wallet_ledger_entry, payment_event

Sheet Scope lines
A1: Output document (draft, deliverable c, Step 01): lines of the split brief. Only open questions (from the Open Items and Risks sheet) and deliberate omissions (from feature discovery) exist so far. Goals, in-scope lines and assumptions are not recorded: they need the original brief.
A3: scope_id | B3: study_id | C3: line_type | D3: statement | E3: maps_to_requirement | F3: scope_source
A4: SC-001 | B4: FDS-01 | C4: Open question | D4: B17 and the 15 to 16 October documents were closed by the lead after an independent review. No teammate has reviewed them yet; a review by Ishaan or Prabhav is welcome. | F4: Open items sheet, RK-01
A5: SC-002 | B5: FDS-01 | C5: Open question | D5: The exchange log is built in the Administration module. The per-field legacy sync rules are still a proposal and need confirmation with the legacy owners. | F5: Open items sheet, RK-02
A6: SC-003 | B6: FDS-01 | C6: Open question | D6: Only 50,000 of 1,000,000 candidates are loaded. Full load needs about 11 GB; the laptop has about 5 GB free. | F6: Open items sheet, RK-03
A7: SC-004 | B7: FDS-01 | C7: Open question | D7: All 11 modules are built; Phase 5 (seeding at scale, timings, indexes, backup, migration) is not started. | F7: Open items sheet, RK-04
A8: SC-005 | B8: FDS-01 | C8: Open question | D8: Roles, a proven session, row-level security on 120 tables, audit writers and 227 access tests are built (16 October). Open: no teammate or independent review; the oracle functions answer for any id (SEC13); policy cost at scale is unmeasured; deployment must set TLS, timeouts and encrypted backups. | F8: Open items sheet, RK-05
A9: SC-006 | B9: FDS-01 | C9: Open question | D9: The rule compliance table has no rule left as not built and 4 partly met (encryption at column level, retention jobs, default views, one more). They are closed as the modules and the deployment steps are built. | F9: Open items sheet, RK-06
A10: SC-007 | B10: FDS-01 | C10: Open question | D10: Subscriptions was built and closed by the lead without an independent review round, and no teammate has reviewed it. The earlier modules each had defects found by review. | F10: Open items sheet, RK-14
A11: SC-008 | B11: FDS-01 | C11: Open question | D11: Sourcing was built and tested (233 tests, nine races) and has had two independent reviews, but no teammate has reviewed it. Before that, no independent review round has been run and no teammate has reviewed it. Its own testing found one lost-row race that a single-session test could not show. | F11: Open items sheet, RK-15
A12: SC-009 | B12: FDS-01 | C12: Open question | D12: The races on seats, devices and sessions were checked with parallel sessions on a scratch database. The SQL test script runs in one session and cannot repeat them. Sourcing now has a repeatable script (tests/concurrency_sourcing.sh); Licences does not. | F12: Open items sheet, RK-12
A13: SC-010 | B13: FDS-01 | C13: Open question | D13: Recruiters, consultants and administrators are erasable (membership, seat and devices end; device text scrubbed) through erase_account(). | F13: Open items sheet, RK-13
A14: SC-011 | B14: FDS-01 | C14: Open question | D14: The per-field sync directions and the conflict rule in the integration table are a proposal and need Prabhav's confirmation with the legacy owners. | F14: Open items sheet, RK-11
A15: SC-012 | B15: FDS-01 | C15: Open question | D15: Locked questionnaires, position required on a published job, requires-comment trigger, recruiter-agency trigger, currency lookup. | F15: Open items sheet, RK-07
... A22: SC-019 | B22: FDS-01 | C22: Out of scope | D22: Custom fields on a prospect: deliberately left out of the design | F22: Feature discovery, FD-058

Sheet Scorecard
B1: Schema rating scorecard
B2: Part A: live formulas on the Tree and Schema register. Part B: a person rates; left blank on purpose.
B4: # | C4: Check | D4: Value | E4: Target | F4: Result | G4: What it proves
B5: 1 | C5: Deepest level in the tree | D5: =MAX(Tree!$E$2:$E$170) | E5: 3 | F5: =IF(D5=E5,"PASS","FAIL") | G5: The tree is no deeper than three levels.
B6: 2 | C6: Nodes with no definition | D6: =COUNTBLANK(Tree!$H$2:$H$170) | E6: 0 | F6: =IF(D6=E6,"PASS","FAIL") | G6: Every section, parameter and sub-parameter says what it means.
B7: 3 | C7: Sub-parameters with no data type | D7: =COUNTIFS(Tree!$E$2:$E$170,3,Tree!$I$2:$I$170,"") | E7: 0 | F7: =IF(D7=E7,"PASS","FAIL") | G7: Every sub-parameter has a type.
B8: 4 | C8: Sub-parameters with no table column | D8: =COUNTIFS(Tree!$E$2:$E$170,3,Tree!$O$2:$O$170,"") | E8: 0 | F8: =IF(D8=E8,"PASS","FAIL") | G8: Every sub-parameter becomes exactly one column.
B9: 5 | C9: Duplicate path ids | D9: =SUMPRODUCT(--(COUNTIF(Tree!$D$2:$D$170,Tree!$D$2:$D$170)>1)) | E9: 0 | F9: =IF(D9=E9,"PASS","FAIL") | G9: Every node has its own id.
B10: 6 | C10: Columns tied to neither a sub-parameter nor a key | D10: =COUNTIFS('Schema register'!$G$2:$G$118,"",'Schema register'!$E$2:$E$118,"") | E10: 0 | F10: =IF(D10=E10,"PASS","FAIL") | G10: No column exists without a reason.
B11: 7 | C11: Enum sub-parameters without a list | D11: =COUNTIF(Tree!$I$2:$I$170,"enum")-COUNTIFS(Tree!$I$2:$I$170,"enum",Tree!$L$2:$L$170,"list:*") | E11: 0 | F11: =IF(D11=E11,"PASS","FAIL") | G11: Every choice field points to an allowed-value list.
B12: 8 | C12: Atomic sub-parameters without an L4 definition | D12: =COUNTIF(Tree!$J$2:$J$170,"atomic")-COUNTIFS('Schema register'!$J$2:$J$118,"*one *value*") | E12: 0 | F12: =IF(D12=E12,"PASS","FAIL") | G12: Every atomic item carries its Pico definition.
B13: 9 | C13: Total parameters (L1 + L2 + L3) | D13: =Summary!B5 | E13: 169 | F13: =IF(D13=E13,"PASS","FAIL") | G13: The dashboard count matches the frozen schema.
B14: 10 | C14: Data values outside the allowed lists | D14: =Measures!C53 | E14: 0 | F14: =IF(D14=E14,"PASS","FAIL") | G14: Every recorded value is one the schema allows, in the Feature discovery, Coverage matrix and NFR register sheets.
B15: 11 | C15: Playbook checks passing | D15: =COUNTIF('Playbook map'!$I$5:$I$14,"PASS") | E15: 7 | F15: =IF(D15=E15,"PASS","FAIL") | G15: The Step 03 playbook points that a formula can test all pass.
C17: Part A score | D17: =COUNTIF(F5:F15,"PASS") | E17: 11 | F17: =D17&" of "&E17
C19: Part B: reviewer rating (1 to 5). Blank until a person scores it.
B20: # | C20: Question for the reviewer | D20: Score 1-5 | G20: Reviewer comment
B21: 1 | C21: Could a new team member read the Tree and know what to record, without asking us?
B22: 2 | C22: Is each definition one clear sentence, with no jargon left unexplained?
B23: 3 | C23: Does each sub-parameter earn its place?
B24: 4 | C24: Is anything the playbook row or the transcript asked for missing?
B25: 5 | C25: Are the allowed-value lists complete and free of overlap?
B26: 6 | C26: Would two different people fill the same record the same way?
C28: Average reviewer score | D28: =IF(COUNT(D21:D26)=0,"not rated yet",AVERAGE(D21:D26))

Sheet Measures
B1: Measures
B2: Counted live from the Feature discovery sheet
B4: Measure | C4: Value | D4: Share | E4: How it is counted
B5: Features and capabilities | C5: =COUNTA('Feature discovery'!$A$4:$A$179) | E5: Rows of the inventory
B6: Features | C6: =COUNTIF('Feature discovery'!$B$4:$B$179,"Feature") | D6: =C6/$C$5 | E6: Level = Feature
B7: Capabilities | C7: =COUNTIF('Feature discovery'!$B$4:$B$179,"Capability") | D7: =C7/$C$5 | E7: Level = Capability
B8: MUST-HAVE | C8: =COUNTIF('Feature discovery'!$K$4:$K$179,"MUST-HAVE") | D8: =C8/$C$5 | E8: Classification
B9: SHOULD-HAVE | C9: =COUNTIF('Feature discovery'!$K$4:$K$179,"SHOULD-HAVE") | D9: =C9/$C$5 | E9: Classification
B10: DIFFERENTIATOR | C10: =COUNTIF('Feature discovery'!$K$4:$K$179,"DIFFERENTIATOR") | D10: =C10/$C$5 | E10: Classification
B11: Traced to a requirement | C11: =COUNTIF('Feature discovery'!$S$4:$S$179,"Traced*") | D11: =C11/$C$5 | E11: Trace status
B12: Flagged NEW INSIGHT | C12: =COUNTIF('Feature discovery'!$S$4:$S$179,"NEW INSIGHT") | D12: =C12/$C$5 | E12: Trace status
B13: Verdict: Exceeds | C13: =COUNTIF('Feature discovery'!$Q$4:$Q$179,"Exceeds") | D13: =C13/$C$5 | E13: Verdict
B14: Verdict: Matches | C14: =COUNTIF('Feature discovery'!$Q$4:$Q$179,"Matches") | D14: =C14/$C$5 | E14: Verdict
B15: Verdict: Falls short | C15: =COUNTIF('Feature discovery'!$Q$4:$Q$179,"Falls short") | D15: =C15/$C$5 | E15: Verdict
B16: Verdict: Not compared | C16: =COUNTIF('Feature discovery'!$Q$4:$Q$179,"Not compared") | D16: =C16/$C$5 | E16: Verdict (own design, no competitor claim)
B17: Built and tested | C17: =COUNTIF('Feature discovery'!$P$4:$P$179,"Built and tested") | D17: =C17/$C$5 | E17: Our coverage
B18: Functional requirements recorded | C18: =COUNTA('Requirements'!$A$4:$A$111) | E18: Rows of the Requirements sheet
B19: Scope lines recorded | C19: =COUNTA('Scope lines'!$A$4:$A$22) | E19: Rows of the Scope lines sheet
B20: NFRs recorded | C20: =COUNTA('NFR register'!$A$4:$A$29) | E20: Rows of the NFR register
B21: with a numeric target | C21: =COUNT('NFR register'!$I$4:$I$29) | D21: =C21/$C$20 | E21: Target value filled
B22: built and tested | C22: =COUNTIF('NFR register'!$R$4:$R$29,"Built and tested") | D22: =C22/$C$20 | E22: Our status
B23: planned | C23: =COUNTIF('NFR register'!$R$4:$R$29,"Planned") | D23: =C23/$C$20 | E23: Our status
B24: proposed (not yet approved) | C24: =COUNTIF('NFR register'!$R$4:$R$29,"Proposed") | D24: =C24/$C$20 | E24: Our status
B26: Data against the schema: values that are not in the allowed list (needs 0)
B27: Sheet and column | C27: Not in list | D27: Rows checked | E27: Allowed list
B28: Feature discovery: Level | C28: =COUNTA('Feature discovery'!$B$4:$B$179)-SUMPRODUCT(COUNTIF('Feature discovery'!$B$4:$B$179,'Allowed values'!$B$28:$B$29)) | D28: =COUNTA('Feature discovery'!$B$4:$B$179) | E28: FeatureLevel
B29: Feature discovery: Category | C29: =COUNTA('Feature discovery'!$F$4:$F$179)-SUMPRODUCT(COUNTIF('Feature discovery'!$F$4:$F$179,'Allowed values'!$B$30:$B$43)) | D29: =COUNTA('Feature discovery'!$F$4:$F$179) | E29: Category
B30: Feature discovery: Persona | C30: =COUNTA('Feature discovery'!$G$4:$G$179)-SUMPRODUCT(COUNTIF('Feature discovery'!$G$4:$G$179,'Allowed values'!$B$44:$B$55)) | D30: =COUNTA('Feature discovery'!$G$4:$G$179) | E30: Persona
B31: Feature discovery: Source type | C31: =COUNTA('Feature discovery'!$H$4:$H$179)-SUMPRODUCT(COUNTIF('Feature discovery'!$H$4:$H$179,'Allowed values'!$B$59:$B$64)) | D31: =COUNTA('Feature discovery'!$H$4:$H$179) | E31: SourceType
B32: Feature discovery: Scope | C32: =COUNTA('Feature discovery'!$J$4:$J$179)-SUMPRODUCT(COUNTIF('Feature discovery'!$J$4:$J$179,'Allowed values'!$B$56:$B$58)) | D32: =COUNTA('Feature discovery'!$J$4:$J$179) | E32: ComparisonScope
B33: Feature discovery: Classification | C33: =COUNTA('Feature discovery'!$K$4:$K$179)-SUMPRODUCT(COUNTIF('Feature discovery'!$K$4:$K$179,'Allowed values'!$B$68:$B$70)) | D33: =COUNTA('Feature discovery'!$K$4:$K$179) | E33: Class
B34: Feature discovery: Class basis | C34: =COUNTA('Feature discovery'!$L$4:$L$179)-SUMPRODUCT(COUNTIF('Feature discovery'!$L$4:$L$179,'Allowed values'!$B$71:$B$77)) | D34: =COUNTA('Feature discovery'!$L$4:$L$179) | E34: ClassBasis
B35: Feature discovery: Confidence | C35: =COUNTA('Feature discovery'!$N$4:$N$179)-SUMPRODUCT(COUNTIF('Feature discovery'!$N$4:$N$179,'Allowed values'!$B$78:$B$80)) | D35: =COUNTA('Feature discovery'!$N$4:$N$179) | E35: Confidence
B36: Feature discovery: Evidence status | C36: =COUNTA('Feature discovery'!$O$4:$O$179)-SUMPRODUCT(COUNTIF('Feature discovery'!$O$4:$O$179,'Allowed values'!$B$21:$B$27)) | D36: =COUNTA('Feature discovery'!$O$4:$O$179) | E36: EvidenceStatus
B37: Feature discovery: Our coverage | C37: =COUNTA('Feature discovery'!$P$4:$P$179)-SUMPRODUCT(COUNTIF('Feature discovery'!$P$4:$P$179,'Allowed values'!$B$90:$B$94)) | D37: =COUNTA('Feature discovery'!$P$4:$P$179) | E37: OurCoverage
B38: Feature discovery: Verdict | C38: =COUNTA('Feature discovery'!$Q$4:$Q$179)-SUMPRODUCT(COUNTIF('Feature discovery'!$Q$4:$Q$179,'Allowed values'!$B$95:$B$99)) | D38: =COUNTA('Feature discovery'!$Q$4:$Q$179) | E38: Verdict
B39: Feature discovery: Trace status | C39: =COUNTA('Feature discovery'!$S$4:$S$179)-SUMPRODUCT(COUNTIF('Feature discovery'!$S$4:$S$179,'Allowed values'!$B$102:$B$104)) | D39: =COUNTA('Feature discovery'!$S$4:$S$179) | E39: TraceState
B40: Coverage matrix: the four competitor columns | C40: =COUNTA('Coverage matrix'!$E$4:$H$126)-SUMPRODUCT(COUNTIF('Coverage matrix'!$E$4:$H$126,'Allowed values'!$B$81:$B$84)) | D40: =COUNTA('Coverage matrix'!$E$4:$H$126) | E40: CellValue
B41: NFR register: Category | C41: =COUNTA('NFR register'!$C$4:$C$29)-SUMPRODUCT(COUNTIF('NFR register'!$C$4:$C$29,'Allowed values'!$B$138:$B$155)) | D41: =COUNTA('NFR register'!$C$4:$C$29) | E41: NfrCategory
B42: NFR register: Comparator | C42: =COUNTA('NFR register'!$H$4:$H$29)-SUMPRODUCT(COUNTIF('NFR register'!$H$4:$H$29,'Allowed values'!$B$156:$B$158)) | D42: =COUNTA('NFR register'!$H$4:$H$29) | E42: Comparator
B43: NFR register: Target status | C43: =COUNTA('NFR register'!$K$4:$K$29)-SUMPRODUCT(COUNTIF('NFR register'!$K$4:$K$29,'Allowed values'!$B$159:$B$160)) | D43: =COUNTA('NFR register'!$K$4:$K$29) | E43: TargetStatus
B44: NFR register: Measured by | C44: =COUNTA('NFR register'!$M$4:$M$29)-SUMPRODUCT(COUNTIF('NFR register'!$M$4:$M$29,'Allowed values'!$B$161:$B$166)) | D44: =COUNTA('NFR register'!$M$4:$M$29) | E44: MeasuredBy
B45: NFR register: Derived from | C45: =COUNTA('NFR register'!$O$4:$O$29)-SUMPRODUCT(COUNTIF('NFR register'!$O$4:$O$29,'Allowed values'!$B$167:$B$171)) | D45: =COUNTA('NFR register'!$O$4:$O$29) | E45: DerivedFrom
B46: NFR register: Our status | C46: =COUNTA('NFR register'!$R$4:$R$29)-SUMPRODUCT(COUNTIF('NFR register'!$R$4:$R$29,'Allowed values'!$B$172:$B$177)) | D46: =COUNTA('NFR register'!$R$4:$R$29) | E46: NfrStatus
B47: Requirements: Actor | C47: =COUNTA('Requirements'!$G$4:$G$111)-SUMPRODUCT(COUNTIF('Requirements'!$G$4:$G$111,'Allowed values'!$B$44:$B$55)) | D47: =COUNTA('Requirements'!$G$4:$G$111) | E47: Persona
B48: Requirements: Priority | C48: =COUNTA('Requirements'!$H$4:$H$111)-SUMPRODUCT(COUNTIF('Requirements'!$H$4:$H$111,'Allowed values'!$B$68:$B$70)) | D48: =COUNTA('Requirements'!$H$4:$H$111) | E48: Class
B49: Requirements: Source type | C49: =COUNTA('Requirements'!$E$4:$E$111)-SUMPRODUCT(COUNTIF('Requirements'!$E$4:$E$111,'Allowed values'!$B$178:$B$182)) | D49: =COUNTA('Requirements'!$E$4:$E$111) | E49: ReqSource
B50: Requirements: Our status | C50: =COUNTA('Requirements'!$K$4:$K$111)-SUMPRODUCT(COUNTIF('Requirements'!$K$4:$K$111,'Allowed values'!$B$183:$B$187)) | D50: =COUNTA('Requirements'!$K$4:$K$111) | E50: ReqStatus
B51: Requirements: Priority basis | C51: =COUNTA('Requirements'!$I$4:$I$111)-SUMPRODUCT(COUNTIF('Requirements'!$I$4:$I$111,'Allowed values'!$B$193:$B$195)) | D51: =COUNTA('Requirements'!$I$4:$I$111) | E51: PriorityBasis
B52: Scope lines: Line type | C52: =COUNTA('Scope lines'!$C$4:$C$22)-SUMPRODUCT(COUNTIF('Scope lines'!$C$4:$C$22,'Allowed values'!$B$188:$B$192)) | D52: =COUNTA('Scope lines'!$C$4:$C$22) | E52: LineType
B53: Total not in list | C53: =SUM(C28:C52)

Sheet Discover log
B1: Discover log
B2: Discover, define, generate, validate, refine: what was done, in order
B4: Round | C4: Step | D4: What was done | E4: Result
B5: 1 | C5: Discover | D5: Read Subramanian S's transcript and the playbook: define the output first, question every parameter, two views consolidated. | E5: Brief written
B6: 1 | C6: Define | D6: Two independent designers each drew the schema from the brief. | E6: Two full drafts
B7: 1 | C7: Generate | D7: Consolidated the two views into one schema and froze it. | E7: 204 parameters, 5 levels (v1.0)
B8: 1 | C8: Validate | D8: Checked every column of the existing feature data against the schema. | E8: All 29 data columns map
B9: 2 | C9: Refine | D9: Cut to three levels, no extra complexity, with parameter names and table columns shown. | E9: Schema v1.1
B10: 3 | C10: Refine | D10: Rebuilt in the Business Workflow Analysis dashboard layout and checked against the playbook row for Step 03; section names moved to the playbook's words; Stage 1 steps and a playbook map added. | E10: Schema v1.2
B11: 6 | C11: Add | D11: Added Step 01 Requirement Analysis Docket as its own group: sections 14 to 18, tables requirement and scope_line, 108 functional requirements and the scope lines that exist so far. Source is Not recorded for every requirement and goals, in-scope lines and assumptions are missing: both need the original brief. | E11: Schema v1.4
B12: 5 | C12: Add | D12: Proposed NFR-21 (Compliance, DPDP Act 2023) and NFR-22 (Accessibility) for the two quality areas the playbook names and no NFR covers; marked Proposed and left out of the Step 04 checks. Added dropdowns on the output sheets, highlights for missing targets, and live status text on the Summary. | E12: Needs team approval
B13: 4 | C13: Validate | D13: Checked every recorded value against the allowed lists. Five columns of the feature data used wording outside the lists (for example 'Traced to requirement' for 'Traced'). Normalised them to the list values, added five list values the real data needed (3 evidence kinds, 2 class bases), and kept the original wording in the last column of the Feature discovery sheet. The Measures sheet now counts any value outside a list. | E13: 0 values outside the lists
B14: 3 | C14: Add | D14: Added Step 04 NFR Discovery: five sections, 18 sub-parameters in one table (19 columns with the study link), an NFR register built from the 20 NFRs in the requirements workbook, and a Step 04 playbook map. | E14: Schema v1.3 (this workbook)
B15: 3 | C15: Open | D15: A person rates the scorecard (Part B); verify the 22 of 53 register rows still marked Known; re-key the output data to the 7 tables. | E15: Pending: the team
